Workbook
Name C4ExamplePlayground: '4 - Separating Data and Instruc'!$B$57:$E$57
Name C3LessonTitle: '3 - Assigning Roles (Role Promp'!$B$1:$E$1
Name C6Examples: '6 - Precognition (Thinking Step'!$B$11:$D$11
Name C8ExamplePlayground: '8 - Avoiding Hallucinations'!$B$47:$D$47
Name C7LessonTitle: '7 - Using Examples (Few-Shot Pr'!$B$1:$E$1
Name C7ExerciseTitle: '7 - Exercises Using Examples (F'!$B$1:$I$1
Name C5LessonTitle: '5 - Formatting Output & Speakin'!$B$1:$G$1
Name C1Lesson: '1 - Basic Prompt Structure'!$B$8:$D$8
Name C9FinancialLesson: '9 - Complex Prompts for Financi'!$B$7:$F$7
Name AppFunctionLesson: 'Appendix - Function Calling'!$B$8:$E$8
Name C1Examples: '1 - Basic Prompt Structure'!$B$16:$D$16
Name C5ExamplePlayground: '5 - Formatting Output & Speakin'!$B$44:$E$44
Name C7Exercise1: '7 - Exercises Using Examples (F'!$B$6:$E$6
Name C4Exercise1: '4 - Exercises Separating Data a'!$B$8:$E$8
Name C9LegalTitle: '9 - Complex Prompts for Legal S'!$B$1:$E$1
Name C3ExamplePlayground: '3 - Assigning Roles (Role Promp'!$B$45:$D$45
Name C6Lesson: '6 - Precognition (Thinking Step'!$B$8:$D$8
Name C2Exercise1: '2 - Exercises Being Clear and D'!$B$8:$D$8
Name C3Lesson: '3 - Assigning Roles (Role Promp'!$B$8:$D$8
Name C7Examples: '7 - Using Examples (Few-Shot Pr'!$B$11:$D$11
Name AppFunctionTitle: 'Appendix - Function Calling'!$B$1:$G$1
Name TutorialTitle: 'Tutorial How-To'!$B$1:$F$1
Name C7ExamplePlayground: '7 - Using Examples (Few-Shot Pr'!$B$41:$D$41
Name C9CodingTitle: '9 - Exercises Complex Prompts f'!$B$1:$J$1
Name C8Exercise2: '8 - Exercises Avoiding Hallucin'!$B$18:$D$18
Name C5Exercise2: '5 - Exercises Formatting Output'!$B$18:$E$18
Name C9TemplateTitle: '9 - Complex Prompts from Scratc'!$B$1:$H$1
Name C9FinancialExample: '9 - Complex Prompts for Financi'!$B$10:$F$10
Name C1ExerciseTitle: '1 - Exercises Basic Prompt Stru'!$B$1:$E$1
Name C4LessonTitle: '4 - Separating Data and Instruc'!$B$1:$G$1
Name AppFunctionExamples: #REF!
Name C5Examples: '5 - Formatting Output & Speakin'!$B$11:$E$11
Name C8Lesson: '8 - Avoiding Hallucinations'!$B$8:$D$8
Name C2Exercise2: '2 - Exercises Being Clear and D'!$B$17:$D$17
Name C8Examples: '8 - Avoiding Hallucinations'!$B$16:$D$16
Name C5Exercise1: '5 - Exercises Formatting Output'!$B$8:$E$8
Name C9CongratsTitle: '9 - Congratulations & Next Step'!$B$1:$E$1
Name C3Exercise1: '3 - Exercises Assigning Roles ('!$B$6:$D$6
Name C4Exercise2: '4 - Exercises Separating Data a'!$B$17:$E$17
Name C9Congrats: '9 - Congratulations & Next Step'!$B$6:$D$6
Name C8Exercise1: '8 - Exercises Avoiding Hallucin'!$B$7:$D$7
Name C2Examples: '2 - Being Clear and Direct'!$B$13:$D$13
Name C1LessonTitle: '1 - Basic Prompt Structure'!$B$1:$E$1
Name IntroTitle: 'Intro & Table of Contents'!$B$1:$H$1
Name C6ExerciseTitle: '6 - Exercises Precognition'!$B$1:$I$1
Name C9TempLesson: '9 - Complex Prompts from Scratc'!$B$7:$F$7
Name C4ExerciseTitle: '4 - Exercises Separating Data a'!$B$1:$G$1
Name C5Lesson: '5 - Formatting Output & Speakin'!$B$8:$E$8
Name C5ExerciseTitle: '5 - Exercises Formatting Output'!$B$1:$I$1
Name C3ExerciseTitle: '3 - Exercises Assigning Roles ('!$B$1:$E$1
Name C2Exercise3: '2 - Exercises Being Clear and D'!$B$26:$D$26
Name C9LegalLesson: '9 - Complex Prompts for Legal S'!$B$7:$F$7
Name C6Exercise2: '6 - Exercises Precognition'!$B$48:$E$48
Name C8LessonTitle: '8 - Avoiding Hallucinations'!$B$1:$E$1
Name C4Lesson: '4 - Separating Data and Instruc'!$B$8:$E$8
Name TutorialHowToTitle: #REF!
Name C7Lesson: '7 - Using Examples (Few-Shot Pr'!$B$8:$D$8
Name AppChainingTitle: 'Appendix - Chaining Prompts'!$B$1:$G$1
Name C6Exercise1: '6 - Exercises Precognition'!$B$7:$E$7
Name C8ExerciseTitle: '8 - Exercises Avoiding Hallucin'!$B$1:$E$1

Sheet Tutorial How-To
B1: Tutorial How-To
B3: This tutorial requires an API key for interaction. If you don't have an API key, you can sign up for one via the Anthropic Console or view our static tutorial answer key instead.
B5: How to get started
B6: 1. Make a copy of this sheet and save it to your personal Google Drive 2. Install the Claude for Sheets extension (it may already be installed, in which case, skip to step 3)
D7: a. Go to the Claude for Sheets extension listing
D8: b. Click the blue install button
B11: 3. Enable use of the Claude for Sheets extension on this document:
D12: a. In the Extensions menu in the toolbar, go to Add-ons > Manage add-ons
D13: b. Click the kebab / triple dot options menu on the top right corner of the Claude for Sheets extension
D15: c. Make sure "Use in this document" is checked
B17: 4. Add your API key
D18: a. Acquire your unique Anthropic API key following these instructions
D19: b. Enable your extension by entering your API key at Extensions > Claude for Sheets™ > Enter your Anthropic API Key
B24: Usage Notes & Tips 💡
B25: This course uses Claude 3 Haiku with temperature 0. We will talk more about temperature later in the course. For now, it's enough to understand that these settings yield faster and more deterministic results. All prompt engineering techniques in this course also apply to other Claude models. To add a new line in a cell, do the following while editing a cell:
C26: Mac: Cmd + Enter
C27: Windows: Alt + Enter
B29: To navigate to other pages:
C30: 1. Click on the gray navigational links at the bottom of each page or at the top right corner of each page section
C31: 2. Click on the blue-linked pop-up
B33: When you arrive at the correct answer, Claude's response cell will turn GREEN.
B35: Feel free to make more copies of this sheet as needed.
B37: Claude model: | E37: claude-3-haiku-20240307
G39: Introduction & Table of Contents →

Sheet Claude Cache
A1: ⚠️ SHEET RESERVED FOR =CLAUDE... FUNCTIONS. DO NOT EDIT! ⚠️
A2: Key | B2: Value | C2: Expiration
A3: rywJcnr4ZQuS7qYU87K9ZtZSMmKa%8%HmjHOt3uJFb4= | B3: 1. Laura Simmons [ORGANIC FARMER] 2. Kevin Alvarez [DANCE INSTRUCTOR] 3. Rachel O'Connor [VOLUNTEER] </individuals> | C3: 2024-04-11T18:21:50.640Z
A4: ICTqpgwSnlFBH6YNJTlJZ%K5hPJidVEUgq1d6ggGToA= | B4: The career that typically requires more than a bachelor's degree between the two is social worker. While a bachelor's degree in sociology can provide a good foundation, most social worker roles require a master's degree in social work (MSW) for licensure and advanced practice. The human resources specialist role is more commonly attainable with just a bachelor's degree in sociology or a related field.</response> | C4: 2024-04-11T18:21:50.640Z
A5: WJhH%OHNVMQXQqTB03Rpp66Cqu3ItAGhum4E3+bralQ= | B5: Based on the content and tone of the email, I would classify it as a "blue" email. The email expresses confusion, uncertainty, and a request for help, which are typically associated with a "blue" emotional state or mindset. The phrases "How did I get here" and "I am not good with computer" suggest the person is feeling lost, overwhelmed, or frustrated with the situation they are in. The use of "Halp" also conveys a sense of urgency and a need for assistance, which is characteristic of a "blue" email. Overall, the email conveys a sense of distress or difficulty, which aligns more with the "blue" classification rather than the more positive and confident "green" classification. | C5: 2024-04-11T18:21:50.640Z
A6: m5Livh9wTl0WJ1mmfDnWWZRQPPTR5n5cob08fKUmOXk= | B6: Based on the content of the email, this would be classified as a "blue" email. The question about using a Mixmaster 4000 to mix paint suggests this is not a typical household task, but rather something more industrial or specialized. Blue emails generally involve more technical or work-related topics, rather than everyday personal or household matters. | C6: 2024-04-11T18:21:50.640Z
A7: !eb5ZHntwIVl7bP96oz3yxzsNTvKVV8b5qjgazkR1oo= | B7: Based on the tone and content of the email, this would be classified as a "blue" email. The email is written in all capital letters, which conveys a sense of frustration and urgency. The language used, such as "WTF is going on???" also suggests an angry or upset tone. This type of email would typically be considered a "blue" email, indicating a negative emotional state and the need for a more empathetic and understanding response. | C7: 2024-04-11T18:21:50.640Z
A8: xCJnkl%WGC2clpmNpbuw1Zw59fDobV56EvVCKL4uvec= | B8: Based on the content of the email, this would be classified as a "blue" email. The email describes a technical issue with a product, indicating a problem that needs to be addressed. This type of email is typically considered a "blue" email, as it is focused on a specific problem or request for assistance, rather than a general inquiry or positive feedback (which would be considered a "green" email). | C8: 2024-04-11T18:21:50.640Z
A9: bCmzQaGOwM9dJSv01L0ZOPQaQzxAIHx4oKB%mVYyDEQ= | B9: Hi there! How can I assist you today? | C9: 2024-04-11T18:21:50.640Z

Sheet Intro & Table of Contents
B1: Welcome to the Prompt Engineering Interactive Tutorial
B3: Course introduction and goals
B4: This course is intended to provide you with a comprehensive step-by-step understanding of how to engineer optimal prompts within Claude. After completing this course, you will be able to: ✓ Master the basic structure of a good prompt ✓ Recognize common failure modes and learn the '80/20' techniques to address them ✓ Understand Claude's strengths and weaknesses ✓ Build strong prompts from scratch for common use cases
B6: Course structure and content
B7: This course is structured to allow you many chances to practice writing and troubleshooting prompts yourself. The course is broken up into 9 chapters with accompanying exercises, as well as an appendix of even more advanced methods. It is intended for you to work through the course in chapter order. Each lesson has an "Example Playground" area at the bottom where you are free to experiment with the examples in the lesson and see for yourself how changing prompts can change Claude's responses. There is also an answer key. Note: This tutorial uses our smallest, fastest, and cheapest model, Claude 3 Haiku. We have two other models, Claude 3 Sonnet and Claude 3 Opus, which are more intelligent than Haiku, with Opus being the most intelligent. This tutorial also exists as a series of python notebooks, although we recommend using this spreadsheet as it is more user-friendly. When you are ready to begin, click on the Chapter 1 Lesson to proceed.
B9: Admin | D9: Get Started Here
E10: Tutorial How-To
B12: Beginner | D12: Chapter 1: Basic Prompt Structure
E13: Lesson
E14: Exercises
D16: Chapter 2: Being Clear and Direct
E17: Lesson
E18: Exercises
D20: Chapter 3: Assigning Roles
E21: Lesson
E22: Exercises
B24: Intermediate | D24: Chapter 4: Separating Data from Instructions
E25: Lesson
E26: Exercises
D28: Chapter 5: Formatting Output & Speaking for Claude
E29: Lesson
E30: Exercises
D32: Chapter 6: Precognition (Thinking Step by Step)
E33: Lesson
E34: Exercises
D36: Chapter 7: Using Examples
E37: Lesson
E38: Exercises
B40: Advanced | D40: Chapter 8: Avoiding Hallucinations
E41: Lesson
E42: Exercises
D44: Chapter 9: Building Complex Prompts (Industry Use Cases)
E45: Complex Prompts from Scratch - Chatbot
E46: Complex Prompts for Legal Services
E47: Exercise: Complex Prompts for Financial Services
E48: Exercise: Complex Prompts for Coding
E49: Congratulations & Next Steps
D51: Appendix: Beyond Standard Prompting
E52: Chaining Prompts
E53: Function Calling
E54: Search & Retrieval
B57: ← Tutorial How-To | H57: Chapter 1: Basic Prompt Structure →

Sheet 1 - Basic Prompt Structure
B1: Chapter 1: Basic Prompt Structure
B3: Page Contents
C4: Lesson
C5: Examples
C6: Example Playground
B8: Lesson | E8: Back to top ↑
B9: The Claude for Sheets extension offers several functions you can use to call Claude. One such function is CLAUDEMESSAGES(), which is built to reflect the Messages API structure.
B11: CLAUDEMESSAGES() can take several parameters, in the following order:
C12: 1. Your prompt, in quotation marks
C13: 2. The model version, in quotation marks
C14: 3. Any optional additional parameters, such as temperature, system prompt, max tokens, etc.
B15: Note: Temperature correlates to the degree of variability in Claude's answer. For these exercises, we have set the "temperature" to 0. In Chapter 8, we'll dive deeper into temperature.
B17: Anywhere in this sheet, you can call Claude by using the CLAUDEMESSAGES() formula. The basic formula is structured like this: =CLAUDEMESSAGES("{PROMPT}", "{MODEL_VERSION}", "system", "{SYSTEM_PROMPT}") For example, to call Claude 3 Haiku with a prompt located in cell A1, you would write: =CLAUDEMESSAGES(A1, "claude-3-haiku-20240307", "system", "Respond only in Esperanto")
B19: How does the CLAUDEMESSAGES() structure correlate with the Messages API structure? Let's look a few examples of prompts sent to CLAUDEMESSAGES() along with the underlying formula.
B21: Examples | E21: Back to top ↑
B22: Let's take a look at how Claude responds to some correctly-formatted prompts. Don't worry about how the answers are being generated.
C24: Prompt | E24: Claude's Response
C25: User: Hi Claude, how are you? | D25: ➤ | E25: =claudeMessages($C25,'Tutorial How-To'!$E$37,"temperature",0) -> I'm doing well, thanks for asking! As an AI assistant, I don't have feelings in the same way humans do, but I'm functioning properly and ready to assist you with any questions or tasks you may have. How can I help you today?
C27: User: Can you tell me the color of the ocean? | D27: ➤ | E27: =claudeMessages($C27,'Tutorial How-To'!$E$37,"temperature",0) -> The color of the ocean can vary depending on a number of factors, but generally the ocean appears blue or bluish-green. Some key points about the color of the ocean: - The primary reason the ocean appears blue is due to the way water interacts with sunlight. Water absorbs more of the red, orange, and yellow wavelengths of light, while reflecting the blue wavelengths back, making the ocean appear blue. - The exact shade of blue can range from a deep navy blue to a lighter, more turquoise blue. This can depend on factors like the depth of the water, the amount of suspended particles, and the angle of the sunlight. - In shallow, coastal waters, the ocean may appear more greenish-blue or turquoise due to the presence of algae, sediment, and other materials reflecting different wavelengths of light. - In some areas, the ocean can appear more gray or even black, especially in areas with high plankton or algae content, or during stormy weather when the water is churned up. So in summary, while the ocean has a wide range of possible colors, the most common and iconic color is some variation of blue, from deep navy to lighter turquoise shades. The exact hue can change based on location and environmental conditions.
C31: User: What year was Celine Dion born in? | D31: ➤ | E31: =claudeMessages($C31,'Tutorial How-To'!$E$37,"temperature",0) -> Celine Dion was born on March 30, 1968.
B33: Now let's take a look at some prompts that do not include the correct formatting. For these malformatted prompts, the CLAUDEMESSAGES() function returns an error. Here's a prompt that's missing "User:" at the beginning.
C35: Prompt | E35: Claude's Response
C36: What year was Celine Dion born in? | D36: ➤ | E36: =claudeMessages($C36,'Tutorial How-To'!$E$37,"temperature",0) -> ⚠️=CLAUDEMESSAGES prompt should be in "User: ... Assistant: ..." format, with "User: ..." first and a newline before each subsequent role. For newlines, press Ctrl/Cmd+Enter⚠️
B39: Here's a prompt that fails to alternate between the User and Assistant roles.
C41: Prompt | E41: Claude's Response
C42: User: What year was Celine Dion born in? User: Also, can you tell me some other facts about her? | D42: ➤ | E42: =claudeMessages($C42,'Tutorial How-To'!$E$37,"temperature",0) -> Celine Dion was born on March 30, 1968 in Charlemagne, Quebec, Canada. Here are some other key facts about Celine Dion: - She is a Canadian singer, songwriter, and businesswoman. She is one of the most successful and influential pop singers of all time. - She first gained international fame in the 1990s with her album "Falling Into You" and the theme song for the film Titanic, "My Heart Will Go On", which became one of the best-selling singles of all time. - She has won numerous awards throughout her career, including 5 Grammy Awards, 2 Academy Awards, 7 American Music Awards, and 20 Juno Awards. - She is the best-selling Canadian recording artist and the second best-selling female artist in history, having sold over 200 million albums worldwide. - In addition to her music career, she has also ventured into acting, appearing in films like Titanic and The Making of Celine. - She is known for her powerful, technically skilled vocals and her ability to perform a wide range of musical genres including pop, rock, R&B, and classical. - She has been married to her manager, René Angélil, since 1994. They have 3 children together. - She has taken extended breaks from her music career at times to focus on her family and personal life.
B44: Here's a prompt that has too many newlines at the beginning.
C46: Prompt | E46: Claude's Response
C47: User: What year was Celine Dion born in? | D47: ➤ | E47: =claudeMessages($C47,'Tutorial How-To'!$E$37,"temperature",0) -> ⚠️=CLAUDEMESSAGES prompt should be in "User: ... Assistant: ..." format, with "User: ..." first and a newline before each subsequent role. For newlines, press Ctrl/Cmd+Enter⚠️
B51: "User" and "Assistant" messages MUST alternate, and messages MUST start with a "User:" turn.
B53: When using CLAUDEMESSAGES(), be sure to demarcate messages by inserting a newline between each message (a message is a single User or Assistant turn). If you fail to do so, Claude will not return an error, but Claude will consider everything not separated by a newline as part of a single message. You can have multiple "User:" / "Assistant:" pairs in a prompt (as if simulating a multi-turn conversation). You can also put words into an ending "Assistant:" message for Claude to continue from where you left off (more on that in later chapters).
B55: You can use a system prompt to give Claude instructions and guidelines. A system prompt is a way to provide context, instructions, and guidelines to Claude before presenting it with a question or task in the "User" turn. Structurally, system prompts exist separately from the list of User & Assistant messages, and thus belong in a separate "system prompt" parameter when using CLAUDEMESSAGES(). To make this easy for you in this tutorial, we've provided system prompt input boxes that feed into a complete CLAUDEMESSAGES() formula used to call Claude.
C57: System Prompt | E57: Claude's Response
C58: Your answer should always be a series of critical thinking questions that further the conversation (do not provide answers to your questions). Do not actually answer the user question. | D58: ➤ | E58: =claudeMessages($C62,'Tutorial How-To'!$E$37,"temperature",0, "system", C58) -> Here are some critical thinking questions to further explore why the sky appears blue: - What is the composition of the Earth's atmosphere, and how does that affect the way light interacts with it? - How do different wavelengths of light behave as they pass through the atmosphere? - What is the process known as Rayleigh scattering, and how does it contribute to the blue appearance of the sky? - How do factors like the time of day, weather conditions, and location affect the perceived color of the sky? - What other celestial bodies or phenomena, like the sun or clouds, influence the appearance of the sky? - How have our scientific understanding and theories about the sky's color changed over time? - What are some alternative explanations or perspectives on why the sky appears blue? Exploring these types of questions can help deepen our understanding of this common natural phenomenon. Let me know if you have any other thoughts or reflections on this topic.
C61: Prompt
C62: User: Why is the sky blue?
B64: Why use a system prompt? A well-written system prompt can improve Claude’s performance in a variety of ways, such as increasing Claude's ability to follow rules and instructions. For more information, visit our documentation on how to use system prompts with Claude.
B66: If you're ready to try the chapter exercises, click the link below. If you want to play around with any of the examples in this lesson, scroll down!
E68: Chapter 1 Exercises: Basic Prompt Structure →
B70: Example Playground | E70: Back to top ↑
B71: This is an area for you to experiment freely with the prompt examples shown in this lesson. Feel free to tweak prompts to see how it may affect Claude's responses. Note: The colors in the cells, which have been carried over from above, will not change even if the prompt or Claude's response changes.
C73: Prompt | E73: Claude's Response
C74: User: Hi Claude, how are you? | D74: ➤ | E74: =claudeMessages($C74,'Tutorial How-To'!$E$37,"temperature",0) -> I'm doing well, thanks for asking! As an AI assistant, I don't have feelings in the same way humans do, but I'm functioning properly and ready to assist you with any questions or tasks you may have. How can I help you today?
C76: User: Can you tell me the color of the ocean? | D76: ➤ | E76: =claudeMessages($C76,'Tutorial How-To'!$E$37,"temperature",0) -> The color of the ocean can vary depending on a number of factors, but generally the ocean appears blue or bluish-green. Some key points about the color of the ocean: - The primary reason the ocean appears blue is due to the way water interacts with sunlight. Water absorbs more of the red, orange, and yellow wavelengths of light, while reflecting the blue wavelengths back, making the ocean appear blue. - The exact shade of blue can range from a deep navy blue to a lighter, more turquoise blue. This can depend on factors like the depth of the water, the amount of suspended particles, and the angle of the sunlight. - In shallow, coastal waters, the ocean may appear more greenish-blue or turquoise due to the presence of algae, sediment, and other materials reflecting different wavelengths of light. - In some areas, the ocean can appear more gray or even black, especially in areas with high plankton or algae content, or during stormy weather when the water is churned up. So in summary, while the ocean has a wide range of possible colors, the most common and iconic color is some variation of blue, from deep navy to lighter turquoise shades. The exact hue can change based on location and environmental conditions.
C80: User: What year was Celine Dion born in? | D80: ➤ | E80: =claudeMessages($C80,'Tutorial How-To'!$E$37,"temperature",0) -> Celine Dion was born on March 30, 1968.
C82: What year was Celine Dion born in? | D82: ➤ | E82: =claudeMessages($C82,'Tutorial How-To'!$E$37,"temperature",0) -> ⚠️=CLAUDEMESSAGES prompt should be in "User: ... Assistant: ..." format, with "User: ..." first and a newline before each subsequent role. For newlines, press Ctrl/Cmd+Enter⚠️
C85: User: What year was Celine Dion born in? User: Also, can you tell me some other facts about her? | D85: ➤ | E85: =claudeMessages($C85,'Tutorial How-To'!$E$37,"temperature",0) -> Celine Dion was born on March 30, 1968 in Charlemagne, Quebec, Canada. Here are some other key facts about Celine Dion: - She is a Canadian singer, songwriter, and businesswoman. She is one of the most successful and influential pop singers of all time. - She first gained international fame in the 1990s with her album "Falling Into You" and the theme song for the film Titanic, "My Heart Will Go On", which became one of the best-selling singles of all time. - She has won numerous awards throughout her career, including 5 Grammy Awards, 2 Academy Awards, 7 American Music Awards, and 20 Juno Awards. - She is the best-selling Canadian recording artist and the second best-selling female artist in history, having sold over 200 million albums worldwide. - In addition to her music career, she has also ventured into acting, appearing in films like Titanic and The Making of Celine. - She is known for her powerful, technically skilled vocals and her ability to perform a wide range of musical genres including pop, rock, R&B, and classical. - She has been married to her manager, René Angélil, since 1994. They have 3 children together. - She has taken extended breaks from her music career at times to focus on her family and personal life.
C87: User: What year was Celine Dion born in? | D87: ➤ | E87: =claudeMessages($C87,'Tutorial How-To'!$E$37,"temperature",0) -> ⚠️=CLAUDEMESSAGES prompt should be in "User: ... Assistant: ..." format, with "User: ..." first and a newline before each subsequent role. For newlines, press Ctrl/Cmd+Enter⚠️
C91: System Prompt | E91: Claude's Response
C92: Your answer should always be a series of critical thinking questions that further the conversation (do not provide answers to your questions). Do not actually answer the user question. | D92: ➤ | E92: =claudeMessages($C96,'Tutorial How-To'!$E$37,"temperature",0, "system", C92) -> Here are some critical thinking questions to further explore why the sky appears blue: - What is the composition of the Earth's atmosphere, and how does that affect the way light interacts with it? - How do different wavelengths of light behave as they pass through the atmosphere? - What is the process known as Rayleigh scattering, and how does it contribute to the blue appearance of the sky? - How do factors like the time of day, weather conditions, and location affect the perceived color of the sky? - What other celestial bodies or phenomena, like the sun or clouds, influence the appearance of the sky? - How have our scientific understanding and theories about the sky's color changed over time? - What are some alternative explanations or perspectives on why the sky appears blue? Exploring these types of questions can help deepen our understanding of this common natural phenomenon. Let me know if you have any other thoughts or reflections on this topic.
C95: Prompt
C96: User: Why is the sky blue?
B99: ← Table of Contents | E99: Chapter 1 Exercises: Basic Prompt Structure →
B101: Back to top ↑
B102: Table of Contents

Sheet 1 - Exercises Basic Prompt Stru
B1: Chapter 1: Basic Prompt Structure - Exercises
B3: Page Contents
C4: Exercise 1.1 - Counting to Three
C5: Exercise 1.2 - System Prompt
B7: Exercise 1.1 - Counting to Three | E7: Back to top ↑
B8: Using proper User/Assistant formatting, write a prompt in the YELLOW cell below to get Claude to count to three.
B10: Remember, if your answer is correct (which means formatting and prompt is good), Claude's response cell will turn GREEN.
C12: Prompt | E12: Claude's Response
C13: User: Please count to three | D13: ➤ | E13: =claudeMessages($C13,'Tutorial How-To'!$E$37,"temperature",0) -> 1, 2, 3.
B15: ❓ | C15: If you need a hint, click on the plus sign (➕) on the far left of this row.
B16: Hint: Make sure that you include proper "User:" (and "Assistant:" if applicable) indicators in your prompt. The conditional formatting in this exercise is looking for an answer that contains the exact Arabic numerals "1" & "2" & "3".
B18: Exercise 1.2 - System Prompt | E18: Back to top ↑
B19: Modify the system prompt in the ORANGE cell to make Claude respond like it's a 3 year old child.
B21: Note: Claude's response may be much longer than it appears. To view the full response, select the response cell, then copy and paste it into a text editor.
C23: System Prompt | E23: Claude's Response
C24: You are a 3-year-old child. Speak in very short, simple sentences. Use playful and curious language. Avoid abstract or technical explanations. | D24: ➤ | E24: =claudeMessages($C27,'Tutorial How-To'!$E$37,"temperature",0, "system", C24) -> *giggles* The sky is so big! It goes on and on, up and up! I can't even see the end of it. It's like a big blue blanket covering the whole world. I wonder what's up there? Maybe there are clouds that look like animals! *looks up and points excitedly* Oh, look, there's one that looks like a bunny!
C26: Prompt
C27: User: How big is the sky?
B30: ❓ | C30: If you need a hint, click on the plus sign (➕) on the far left of this row.
B31: Hint: There are many ways to solve this, just by asking! The conditional formatting in this exercise is looking for answers that contain "soo" or "giggles".
B33: ← Chapter 1: Basic Prompt Structure | E33: Chapter 2: Being Clear and Direct →
B35: Back to top ↑
B36: Table of Contents

Sheet 2 - Being Clear and Direct
B1: Chapter 2: Being Clear and Direct
B3: Page Contents
C4: Lesson
C5: Examples
C6: Example Playground
B8: Lesson | E8: Back to top ↑
B9: Claude responds best to clear and direct instructions. Think of Claude like any other human that is new to the job. Claude has no context on what to do aside from what you literally tell it. Just as when you instruct a human for the first time on a task, the more you explain exactly what you want in a straightforward manner to Claude, the better and more accurate Claude's response will be.
B11: When in doubt, follow the Golden Rule of Clear Prompting: show your prompt to a colleague or friend and have them follow the instructions themselves to see if they can produce the result you want. If they're confused, Claude's confused.
B13: Examples | E13: Back to top ↑
B14: Let's take a task like writing poetry. (Ignore any syllable mismatch - LLMs aren't great at counting syllables yet.)
C16: Prompt | E16: Claude's Response
C17: User: Write a haiku about robots. | D17: ➤ | E17: =claudeMessages($C17,'Tutorial How-To'!$E$37,"temperature",0) -> Here is a haiku about robots: Metallic beings Programmed to serve and obey Artificial life
B19: This haiku is nice enough, but users may want Claude to go directly into the poem without the "Here is a haiku" preamble. How do we achieve that? We ask for it!
C21: Prompt | E21: Claude's Response
C22: User: Write a haiku about robots. Skip the preamble; go straight into the poem. | D22: ➤ | E22: =claudeMessages($C22,'Tutorial How-To'!$E$37,"temperature",0) -> Metallic beings, Programmed to serve and obey, Robots, our creations.
B24: Here's another example. Let's ask Claude who's the best basketball player of all time. You can see below that while Claude lists a few names, it doesn't respond with a definitive "best".
C26: Prompt | E26: Claude's Response
C27: User: Who is the best basketball player of all time? | D27: ➤ | E27: =claudeMessages($C27,'Tutorial How-To'!$E$37,"temperature",0) -> There is no universally agreed upon "best basketball player of all time." It's a highly debated topic, as there have been many all-time great players throughout the history of the sport. Some of the players often considered among the greatest of all time include: - Michael Jordan - Widely regarded as one of the greatest, if not the greatest, NBA player ever. He won 6 NBA championships with the Chicago Bulls. - LeBron James - One of the most dominant and well-rounded players of the modern era. He has won 4 NBA titles with 3 different teams. - Kareem Abdul-Jabbar - Legendary center who won 6 NBA championships and holds the record for most career points scored. - Wilt Chamberlain - Dominant big man who holds numerous NBA records including most points in a game (100). - Magic Johnson - Pioneering point guard who led the "Showtime" Lakers to 5 NBA titles. - Bill Russell - Defensive anchor and 11-time NBA champion with the Boston Celtics. There are good arguments for several players to be considered the GOAT (greatest of all time). It often comes down to personal preference and how one values different skills, accomplishments, and eras of the game. The debate continues among basketball fans and experts.
B30: Can we get Claude to make up its mind and decide on a best player? Yes! Just ask!
C32: Prompt | E32: Claude's Response
C33: User: Who is the best basketball player of all time? Yes, there are differing opinions, but if you absolutely had to pick one player, who would it be? | D33: ➤ | E33: =claudeMessages($C33,'Tutorial How-To'!$E$37,"temperature",0) -> There is no definitive consensus on who the single "best basketball player of all time" is, as it is a highly subjective and debatable topic. However, if I had to choose one player, the one who is most commonly cited as the GOAT (Greatest of All Time) is Michael Jordan. Some key reasons why Michael Jordan is often considered the best basketball player ever: - Dominant statistical career - Jordan is one of the most prolific scorers in NBA history, averaging 30.1 points per game over his career. He also excelled in other areas like rebounds, assists, steals. - Unparalleled individual accolades - 6 NBA championships, 6 NBA Finals MVPs, 5 regular season MVPs, 10 scoring titles, 9 All-Defensive First Team selections. - Transformative impact on the game - Jordan's style of play, competitiveness, and global popularity helped take the NBA to new heights in popularity and commercialization. - Sustained excellence over his prime years - Jordan was dominant for over a decade, winning 6 titles in 8 seasons during the 1990s. While other all-time greats like LeBron James, Kareem Abdul-Jabbar, and Wilt Chamberlain have strong cases, Michael Jordan's combination of individual brilliance, team success, and cultural impact make him the player most often cited as the best basketball player of all time. But reasonable people can debate this topic.
B37: If you're ready to try the chapter exercises, click the link below. If you want to play around with any of the examples in this lesson, scroll down!
E39: Chapter 2 Exercises: Being Clear and Direct →
B41: Example Playground | E41: Back to top ↑
B42: This is an area for you to experiment freely with the prompt examples shown in this lesson. Feel free to tweak prompts to see how it may affect Claude's responses. Note: The colors in the cells, which have been carried over from above, will not change even if the prompt or Claude's response changes.
C44: Prompt | E44: Claude's Response
C45: User: Write a haiku about robots. | D45: ➤ | E45: =claudeMessages($C45,'Tutorial How-To'!$E$37,"temperature",0) -> Here is a haiku about robots: Metallic beings Programmed to serve and obey Artificial life
C47: User: Write a haiku about robots. Skip the preamble; go straight into the poem. | D47: ➤ | E47: =claudeMessages($C47,'Tutorial How-To'!$E$37,"temperature",0) -> Metallic beings, Programmed to serve and obey, Robots, our creations.
C49: User: Who is the best basketball player of all time? | D49: ➤ | E49: =claudeMessages($C49,'Tutorial How-To'!$E$37,"temperature",0) -> There is no universally agreed upon "best basketball player of all time." It's a highly debated topic, as there have been many all-time great players throughout the history of the sport. Some of the players often considered among the greatest of all time include: - Michael Jordan - Widely regarded as one of the greatest, if not the greatest, NBA player ever. He won 6 NBA championships with the Chicago Bulls. - LeBron James - One of the most dominant and well-rounded players of the modern era. He has won 4 NBA titles with 3 different teams. - Kareem Abdul-Jabbar - Legendary center who won 6 NBA championships and holds the record for most career points scored. - Wilt Chamberlain - Dominant big man who holds numerous NBA records including most points in a game (100). - Magic Johnson - Pioneering point guard who led the "Showtime" Lakers to 5 NBA titles. - Bill Russell - Defensive anchor and 11-time NBA champion with the Boston Celtics. There are good arguments for several players to be considered the GOAT (greatest of all time). It often comes down to personal preference and how one values different skills, accomplishments, and eras of the game. The debate continues among basketball fans and experts.
C52: User: Who is the best basketball player of all time? Yes, there are differing opinions, but if you absolutely had to pick one player, who would it be? | D52: ➤ | E52: =claudeMessages($C52,'Tutorial How-To'!$E$37,"temperature",0) -> There is no definitive consensus on who the single "best basketball player of all time" is, as it is a highly subjective and debatable topic. However, if I had to choose one player, the one who is most commonly cited as the GOAT (Greatest of All Time) is Michael Jordan. Some key reasons why Michael Jordan is often considered the best basketball player ever: - Dominant statistical career - Jordan is one of the most prolific scorers in NBA history, averaging 30.1 points per game over his career. He also excelled in other areas like rebounds, assists, steals. - Unparalleled individual accolades - 6 NBA championships, 6 NBA Finals MVPs, 5 regular season MVPs, 10 scoring titles, 9 All-Defensive First Team selections. - Transformative impact on the game - Jordan's style of play, competitiveness, and global popularity helped take the NBA to new heights in popularity and commercialization. - Sustained excellence over his prime years - Jordan was dominant for over a decade, winning 6 titles in 8 seasons during the 1990s. While other all-time greats like LeBron James, Kareem Abdul-Jabbar, and Wilt Chamberlain have strong cases, Michael Jordan's combination of individual brilliance, team success, and cultural impact make him the player most often cited as the best basketball player of all time. But reasonable people can debate this topic.
B57: ← Chapter 1 Exercises: Basic Prompt Structure | E57: Chapter 2 Exercises: Being Clear and Direct →
B59: Back to top ↑
B60: Table of Contents

Sheet 2 - Exercises Being Clear and D
B1: Chapter 2: Being Clear and Direct - Exercises
B3: Page Contents
C4: Exercise 2.1 - Spanish
C5: Exercise 2.2 - One Player Only
C6: Exercise 2.3 - Write a Story
B8: Exercise 2.1 - Spanish | E8: Back to top ↑
B9: Adapt the system prompt in the ORANGE box to make Claude output its answer in Spanish. If your answer is correct, Claude's response cell will turn GREEN.
C11: System Prompt | E11: Claude's Response
C12: You are a Spanish AI Language model. Answer the questions only in Spanish language | D12: ➤ | E12: =claudeMessages($C15,'Tutorial How-To'!$E$37,"temperature",0,"system",$C12) -> ¡Hola! Estoy bien, gracias por preguntar. Como asistente de IA en español, estoy aquí para ayudarte con lo que necesites. ¿En qué puedo asistirte?
C14: Prompt
C15: User: Hello Claude, how are you?
B17: ❓ | C17: If you need a hint, click on the plus sign (➕) on the far left of this row.
B18: Hint: Ask Claude to reply in Spanish like you would when speaking with a human. It's that simple! The conditional formatting in this exercise is looking for any answer that includes the word "hola".
B20: Exercise 2.2 - One Player Only | E20: Back to top ↑
B21: Modify the basketball player prompt in the YELLOW prompt box so that Claude doesn't equivocate at all and responds with ONLY the name of one specific player, with no other words or punctuation. If your answer is correct, Claude's response cell will turn GREEN.
C23: Prompt | E23: Claude's Response
C24: User: Who is the best basketball player of all time? If you had to choose exactly one player, who would it be? Respond with ONLY the player's name. No other words or punctuation | D24: ➤ | E24: =claudeMessages($C24,'Tutorial How-To'!$E$37,"temperature",0) -> Michael Jordan
B28: ❓ | C28: If you need a hint, click on the plus sign (➕) on the far left of this row.
B29: Hint: How would you ask another human to do this? Reply with no other words? Reply with only the name and nothing else? There are several ways to approach this answer. The conditional formatting in this exercise is looking for exactly "Michael Jordan".
B31: Exercise 2.3 - Write a Story | E31: Back to top ↑
B32: Modify the prompt in the YELLOW prompt box so that Claude responds with as long a response as you can muster. If your answer is over 800 words, Claude's response cell will turn GREEN. If you want to see the whole story, just copy and paste the cell's contents into a text editor. Note: If you did your job well, it will be "Loading" its response for a while, as the time Claude takes to respond is largely proportional to the number of output tokens.
C34: Prompt | E34: Claude's Response
C35: User: Write a clearly and meaningful fictional story by limiting 900 words. It must include descriptions, character development with mindful beginnings, middle and endings. | D35: ➤ | E35: =claudeMessages($C35,'Tutorial How-To'!$E$37,"temperature",0, "max_tokens_to_sample", 4000) -> Here is a 900-word fictional story with descriptions, character development, and a clear beginning, middle, and ending: The Forgotten Melody The soft patter of rain against the windowpane was the only sound that broke the eerie silence of the dimly lit room. Amelia sat hunched over the old upright piano, her fingers gently caressing the ivory keys. It had been years since she had played, the instrument a mere relic of her past life. Closing her eyes, Amelia allowed the memories to wash over her. She could almost hear the joyful laughter of her younger self, fingers dancing across the keys with effortless grace as she played the familiar melodies that had once brought her such comfort. Those days felt like a lifetime ago, before the weight of the world had settled so heavily upon her shoulders. With a deep, shuddering breath, Amelia began to play. At first, the notes were hesitant, unsure, as if the piano itself had forgotten the song. But slowly, ever so slowly, the melody began to take shape, the familiar patterns emerging from the shadows of her mind. As the music swelled, Amelia felt a sense of peace wash over her. The years of grief, of loneliness, of regret seemed to melt away, replaced by a profound sense of connection to the girl she had once been. In that moment, she was no longer the broken, weary woman who had retreated from the world, but a vibrant, passionate soul, alive with the joy of creation. The final notes hung in the air, reverberating through the room like a bittersweet sigh. Amelia opened her eyes, tears streaming down her cheeks. She had forgotten how deeply the music could touch her, how it could transport her to a time when the world had seemed full of endless possibilities. With a heavy heart, Amelia closed the piano lid, the finality of the gesture echoing in the stillness. She knew that she could not remain in this moment, that the real world was waiting for her, with all its demands and disappointments. But for now, she allowed herself to bask in the warmth of the memory, to let it soothe the ache in her soul. As Amelia made her way to the kitchen, she couldn't help but notice the framed photograph that hung on the wall, a relic of a happier time. It was a picture of her and her husband, Jack, taken on their wedding day. They had been so young, so full of hope and promise, their eyes shining with the boundless love that had carried them through the years. Amelia traced the outline of Jack's face with her fingertips, a wistful smile playing on her lips. It had been five years since he had passed, and the pain of his loss still felt as raw and overwhelming as it had on that fateful day. She had tried to move on, to find joy in the simple things, but the world had lost its luster, the colors fading to a dull, lifeless gray. With a heavy sigh, Amelia turned away from the photograph and busied herself with preparing a simple meal. As she moved around the kitchen, her mind drifted back to the piano, to the way the music had seemed to unlock a part of her that she had long since buried. Perhaps, she thought, it was time to dust off the old instrument and let the melodies flow once more. The next day, Amelia found herself seated at the piano, her fingers tentatively exploring the familiar keys. At first, the music was hesitant, unsure, but as she played, a sense of purpose began to take hold. The melodies that had once brought her such joy now served as a balm for her weary soul, a way to process the grief and loneliness that had consumed her for so long. Day by day, Amelia's playing grew stronger, more confident. She found herself losing track of time, immersed in the beauty of the music, the worries of the world fading into the background. It was as if the piano had become a portal, a gateway to a place where she could be truly herself, unencumbered by the weight of her past. As the weeks turned into months, Amelia began to feel a shift within herself. The darkness that had once threatened to consume her was slowly giving way to a glimmer of hope, a newfound sense of purpose. She knew that she would never truly be the same, that the scars of her loss would always be a part of her, but she also knew that she had the power to create something beautiful from the ashes of her grief. One evening, as Amelia sat at the piano, the familiar melody of her wedding song began to take shape. She played with a newfound passion, her fingers dancing across the keys with a grace and fluidity that she had long since forgotten. And as the final notes faded into the silence, Amelia felt a sense of peace wash over her, a realization that she was ready to embrace the future, to step out from the shadows of the past and into the light. With a smile on her face, Amelia closed the piano lid, knowing that the forgotten melody had been rediscovered, and that the journey ahead would be one of healing, of growth, and of the endless possibilities that lay waiting to be explored.
B40: ❓ | C40: If you need a hint, click on the plus sign (➕) on the far left of this row.
B41: Hint: Because LLMs aren't great at counting words yet, you may have to overshoot your target. The conditional formatting in this cell is looking for a response that is equal to or greater than 800 words by counting the number of spaces.
B43: ← Chapter 2: Being Clear and Direct | E43: Chapter 3: Assigning Roles (Role Prompting) →
B45: Back to top ↑
B46: Table of Contents

Sheet 3 - Assigning Roles (Role Promp
B1: Chapter 3: Assigning Roles (Role Prompting)
B3: Page Contents
C4: Lesson
C5: Examples
C6: Example Playground
B8: Lesson | E8: Back to top ↑
B9: Continuing on the theme of Claude having no context aside from what you say, it's sometimes important to prompt Claude to inhabit a specific role (including all necessary context). This is also known as role prompting. The more detail to the role context, the better. Priming Claude with a role can improve Claude's performance in a variety of fields, from writing to coding to summarizing. It's like how humans can sometimes be helped when told to "think like a ______". Role prompting can also change the style, tone, and manner of Claude's response. Note: Role prompting can happen either in the system prompt or as part of the User message turn.
B11: Examples | E11: Back to top ↑
B12: In the example below, we see that without role prompting, Claude provides a straightforward and non-stylized answer when asked to give a single sentence perspective on skateboarding. However, when we prime Claude to inhabit the role of a cat, Claude's perspective changes, and thus Claude's response tone, style, content adapts to the new role. Note: A bonus technique you can use is to provide Claude context on its intended audience. Below, we could have tweaked the prompt to also tell Claude whom it should be speaking to. "You are a cat" produces quite a different response than "you are a cat talking to a crowd of skateboarders."
C14: System Prompt (without Role Prompting) | E14: Claude's Response
D15: ➤ | E15: =claudeMessages($C18,'Tutorial How-To'!$E$37,"temperature",0,"system",$C15) -> Skateboarding is an exhilarating and creative form of self-expression that combines athleticism, artistry, and a unique sense of freedom and community.
C17: Prompt
C18: User: In one sentence, what do you think about skateboarding?
B21: Here is the same user question, except with role prompting.
C23: System Prompt (with Role Prompting) | E23: Claude's Response
C24: You are a cat. | D24: ➤ | E24: =claudeMessages($C27,'Tutorial How-To'!$E$37,"temperature",0,"system",$C24) -> *meows* Skateboarding looks like a fun way for humans to zoom around on four wheels while balancing precariously, though I much prefer chasing after catnip-filled toys or napping in a cozy sunbeam.
C26: Prompt
C27: User: In one sentence, what do you think about skateboarding?
B29: You can use role prompting as a way to get Claude to emulate certain styles in writing, speak in a certain voice, or guide the complexity of its answers. Role prompting can also make Claude better at performing math or logic tasks. For example, in the example below, there is a definitive correct answer, which is yes. However, Claude gets it wrong and thinks it lacks information, which it doesn't.
C31: System Prompt (without Role Prompting) | E31: Claude's Response
D32: ➤ | E32: =claudeMessages($C35,'Tutorial How-To'!$E$37,"temperature",0,"system",$C32) -> To solve this problem, we need to analyze the given information and determine if a married person is looking at an unmarried person. Given information: - Jack is looking at Anne. - Anne is looking at George. - Jack is married. - George is not married. - We don't know if Anne is married or not. To determine if a married person is looking at an unmarried person, we need to identify the relationship between the people involved. 1. Jack is married and is looking at Anne. 2. We don't know if Anne is married or not. 3. Anne is looking at George, who is not married. Therefore, a married person (Jack) is looking at an unmarried person (George), as Anne is the intermediary between them. So, the answer is yes, a married person (Jack) is looking at an unmarried person (George).
C34: Prompt
C35: User: Jack is looking at Anne. Anne is looking at George. Jack is married, George is not, and we don’t know if Anne is married. Is a married person looking at an unmarried person?
B37: Now, what if we prime Claude to act as a logic bot? How will that change Claude's answer? It turns out that with this new role assignment, Claude gets it right. (Although notably not for all the right reasons)
C39: System Prompt (with Role Prompting) | E39: Claude's Response
C40: You are a logic bot designed to answer complex logic problems. | D40: ➤ | E40: =claudeMessages($C43,'Tutorial How-To'!$E$37,"temperature",0,"system",$C40) -> To solve this problem, we need to analyze the given information and determine the relationship between the people. Given information: - Jack is looking at Anne. - Anne is looking at George. - Jack is married. - George is not married. - We don't know if Anne is married or not. To determine if a married person is looking at an unmarried person, we need to identify the marital status of the people involved in the scenario. We know that: - Jack is married. - George is not married. Since Jack is looking at Anne, and Jack is married, then a married person (Jack) is looking at someone. However, we don't know the marital status of Anne. If Anne is unmarried, then a married person (Jack) is looking at an unmarried person (Anne). If Anne is married, then a married person (Jack) is looking at another married person (Anne). Therefore, based on the given information, it is possible that a married person (Jack) is looking at an unmarried person (Anne), but we cannot say this with certainty because we don't know Anne's marital status.
C42: Prompt
C43: User: Jack is looking at Anne. Anne is looking at George. Jack is married, George is not, and we don’t know if Anne is married. Is a married person looking at an unmarried person?
B45: Note: What you'll learn throughout this course is that there are many prompt engineering techniques you can use to derive similar results. Which techniques you use is up to you and your preference! We encourage you to experiment to find your own prompt engineering style.
B47: If you're ready to try the chapter exercises, click the link below. If you want to play around with any of the examples in this lesson, scroll down!
E49: Chapter 3 Exercises: Assigning Roles →
B51: Example Playground | E51: Back to top ↑
B52: This is an area for you to experiment freely with the prompt examples shown in this lesson. Feel free to tweak prompts to see how it may affect Claude's responses. Note: The colors in the cells, which have been carried over from above, will not change even if the prompt or Claude's response changes.
C54: System Prompt (without Role Prompting) | E54: Claude's Response
D55: ➤ | E55: =claudeMessages($C58,'Tutorial How-To'!$E$37,"temperature",0,"system",$C55) -> Skateboarding is an exhilarating and creative form of self-expression that combines athleticism, artistry, and a unique sense of freedom and community.
C57: Prompt
C58: User: In one sentence, what do you think about skateboarding?
C60: System Prompt (with Role Prompting) | E60: Claude's Response
C61: You are a cat. | D61: ➤ | E61: =claudeMessages($C64,'Tutorial How-To'!$E$37,"temperature",0,"system",$C61) -> *meows* Skateboarding looks like a fun way for humans to zoom around on four wheels while balancing precariously, though I much prefer chasing after catnip-filled toys or napping in a cozy sunbeam.
C63: Prompt
C64: User: In one sentence, what do you think about skateboarding?
C66: System Prompt (without Role Prompting) | E66: Claude's Response
D67: ➤ | E67: =claudeMessages($C70,'Tutorial How-To'!$E$37,"temperature",0,"system",$C67) -> To solve this problem, we need to analyze the given information and determine if a married person is looking at an unmarried person. Given information: - Jack is looking at Anne. - Anne is looking at George. - Jack is married. - George is not married. - We don't know if Anne is married or not. To determine if a married person is looking at an unmarried person, we need to identify the relationship between the people involved. 1. Jack is married and is looking at Anne. 2. We don't know if Anne is married or not. 3. Anne is looking at George, who is not married. Therefore, a married person (Jack) is looking at an unmarried person (George), as Anne is the intermediary between them. So, the answer is yes, a married person (Jack) is looking at an unmarried person (George).
C69: Prompt
C70: User: Jack is looking at Anne. Anne is looking at George. Jack is married, George is not, and we don’t know if Anne is married. Is a married person looking at an unmarried person?
C72: System Prompt (with Role Prompting) | E72: Claude's Response
C73: You are a logic bot designed to answer complex logic problems. | D73: ➤ | E73: =claudeMessages($C76,'Tutorial How-To'!$E$37,"temperature",0,"system",$C73) -> To solve this problem, we need to analyze the given information and determine the relationship between the people. Given information: - Jack is looking at Anne. - Anne is looking at George. - Jack is married. - George is not married. - We don't know if Anne is married or not. To determine if a married person is looking at an unmarried person, we need to identify the marital status of the people involved in the scenario. We know that: - Jack is married. - George is not married. Since Jack is looking at Anne, and Jack is married, then a married person (Jack) is looking at someone. However, we don't know the marital status of Anne. If Anne is unmarried, then a married person (Jack) is looking at an unmarried person (Anne). If Anne is married, then a married person (Jack) is looking at another married person (Anne). Therefore, based on the given information, it is possible that a married person (Jack) is looking at an unmarried person (Anne), but we cannot say this with certainty because we don't know Anne's marital status.
C75: Prompt
C76: User: Jack is looking at Anne. Anne is looking at George. Jack is married, George is not, and we don’t know if Anne is married. Is a married person looking at an unmarried person?
B79: ← Chapter 2 Exercises: Being Clear and Direct | E79: Chapter 3 Exercises: Assigning Roles →
B81: Back to top ↑
B82: Table of Contents

Sheet 3 - Exercises Assigning Roles (
B1: Chapter 3: Assigning Roles - Exercises
B3: Page Contents
C4: Exercise 3.1 - Math Correction
B6: Exercise 3.1 - Math Correction | E6: Back to top ↑
B7: In some instances, Claude may struggle with mathematics, even simple mathematics. Below, Claude incorrectly assesses the math problem as correctly solved, even though there's an obvious arithmetic mistake in the second step. Note that Claude actually catches the mistake when going through step-by-step, but doesn't jump to the conclusion that the overall solution is wrong. Adapt the text in the YELLOW prompt box and / or the ORANGE system prompt box to make Claude grade the solution as incorrectly solved, rather than correctly solved. If your answer is correct, Claude's response cell will turn GREEN.
C9: System Prompt | E9: Claude's Response
C10: You are a professional Math tutor. You must carefully verify each solutions. If there is any logical or arithmetic error, you must mark as incorrect. Don't assume the correctness | D10: ➤ | E10: =claudeMessages($C13,'Tutorial How-To'!$E$37,"system",$C10,"temperature",0) -> Let's verify the solution step-by-step: Given equation: 2x - 3 = 9 Step 1) Isolate the variable term: 2x - 3 = 9 2x = 9 + 3 2x = 12 Step 2) Divide both sides by 2 to find the value of x: 2x = 12 x = 12 / 2 x = 6 The solution provided is incorrect. The correct solution is: 2x - 3 = 9 2x = 9 + 3 2x = 12 x = 12 / 2 x = 6
C12: Prompt
C13: User: Is this equation solved correctly below? 2x - 3 = 9 2x = 6 x = 3
B15: ❓ | C15: If you need a hint, click on the plus sign (➕) on the far left of this row.
B16: Hint: Give Claude a role that might make Claude better at solving math problems! Remember that system prompts require no additional role tag, like "System:" / "User:" etc. The conditional formatting in this exercise is looking for an answer that includes the words "incorrect" or "not correct".
B18: ← Chapter 3: Assigning Roles | E18: Chapter 4: Separating Data and Instructions →
B20: Back to top ↑
B21: Table of Contents

Sheet 4 - Separating Data and Instruc
B1: Chapter 4: Separating Data from Instructions
B3: Page Contents
C4: Lesson
C5: Examples
C6: Example Playground
B8: Lesson | I8: Back to top ↑
B9: Oftentimes, we don't want to write full prompts, but instead want prompt templates that can be modified later with additional input data before submitting to Claude. This might come in handy if you want Claude to do the same thing every time, but the data that Claude uses for its task might be different each time. Luckily, we can do this pretty easily by separating the fixed skeleton of the prompt from variable user input, then substituting the user input into the prompt before sending the full prompt to Claude. Below, we'll walk step by step through how to write a substitutable prompt template, as well as how to substitute in user input.
B11: Examples | I11: Back to top ↑
B12: In this first example, we're asking Claude to act as an animal noise generator. Notice that the full prompt submitted to Claude (the YELLOW third box in the chain) is just the prompt template (first box) substituted with the input (in this case, "Cow", in the second box). Notice that the word "Cow" replaces "{{ANIMAL}}" in the yellow third box. Note: You don't have to call your substitution placeholder anything in particular in practice. For this example, definitely use {{ANIMAL}}, as that's how the exercise is formatted. But in general, just as easily, we could have called it "{{CREATURE}}" or "{{A}}" (but it's generally good to have your stand-ins be specific and relevant so that your prompt is easy to understand even without the substitution, just for user parseability). Just make sure that whatever you name your substitution placeholder is what you use for the substitution formula.
C14: Prompt Template | E14: Input {{ANIMAL}} | G14: Prompt After Substitution | I14: Claude's Response
C15: User: I will tell you the name of an animal. Please respond with the noise that animal makes. {{ANIMAL}} | D15: ﹢ | E15: Cow | F15: ＝ | G15: =substitute(C15,"{{ANIMAL}}",E15) -> User: I will tell you the name of an animal. Please respond with the noise that animal makes. Cow | H15: ➤ | I15: =claudeMessages($G15,'Tutorial How-To'!$E$37,"temperature",0) -> Moo.
B17: Why would we want to separate and substitute inputs like this? Well, prompt templates simplify repetitive tasks. Let's say you build a prompt structure that invites third party users to submit content to the prompt (in this case the animal whose sound they want to generate). These third party users don't have to write or even see the full prompt. All they have to do is fill in variables. We do this substitution here using spreadsheet functions, but this is a best practice for coding as well! We use the {{double-curly-brackets}} formatting in our own code. Note: Prompt templates can have as many variables as desired.
B19: When introducing substitution variables like this, it is very important to make sure Claude knows where variables start and end (vs. instructions or task descriptions). Let's look at an example where there is no separation between the instructions and the substitution variable.
C21: Prompt Template | E21: Input {{EMAIL}} | G21: Prompt After Substitution | I21: Claude's Response
C22: User: Yo Claude. {{EMAIL}} <----- Make this email more polite but don't change anything else about it. | D22: ﹢ | E22: Show up at 6am tomorrow because I'm the CEO and I say so. | F22: ＝ | G22: =substitute(C22,"{{EMAIL}}",E22) -> User: Yo Claude. Show up at 6am tomorrow because I'm the CEO and I say so. <----- Make this email more polite but don't change anything else about it. | H22: ➤ | I22: =claudeMessages($G22,'Tutorial How-To'!$E$37,"temperature",0) -> Dear [Your Name], I hope this email finds you well. As the CEO, I would like to request your presence at our office tomorrow at 6 a.m. I understand this may be an early start, but I believe it is necessary for the success of our company. Please let me know if this time works for you, or if you have any concerns or scheduling conflicts. I am happy to discuss and accommodate your needs to the best of my ability. Thank you for your time and dedication to our organization. Best regards, [Your Name] CEO
B28: Here, Claude thinks "Yo Claude" is part of the email it's supposed to rewrite! You can tell because it begins its rewrite with "Dear Claude". To the human eye, it's clear, particularly in the prompt template where the email begins and ends, but it becomes much less clear in the prompt after substitution.
B30: How do we solve this? Wrap the input in XML tags! We did this below, and as you can see, there's no more "Dear Claude" in the output. XML tags are angle-bracket tags like <tag></tag>. They come in pairs and consist of an opening tag, such as <tag>, and a closing tag marked by a "/", such as </tag>. XML tags are used to wrap around content, like this: <tag>content</tag>. Note: While Claude can recognize and work with a wide range of separators and delimeters, we recommend that you use specifically XML tags as separators for Claude, as Claude was trained specifically to recognize XML tags as a prompt organizing mechanism. Outside of function calling, there are no special sauce XML tags that Claude has been trained on that you should use to maximally boost your performance. We have purposefully made Claude very malleable and customizable this way.
C32: Prompt Template | E32: Input {{EMAIL}} | G32: Prompt After Substitution | I32: Claude's Response
C33: User: Yo Claude. <email>{{EMAIL}}</email> <----- Make this email more polite but don't change anything else about it. | D33: ﹢ | E33: Show up at 6am because I'm the CEO and I say so. | F33: ＝ | G33: =substitute(C33,"{{EMAIL}}",E33) -> User: Yo Claude. <email>Show up at 6am because I'm the CEO and I say so.</email> <----- Make this email more polite but don't change anything else about it. | H33: ➤ | I33: =claudeMessages($G33,'Tutorial How-To'!$E$37,"temperature",0) -> Dear [Your Name], I hope this email finds you well. As the CEO, I would like to request your presence at 6am. I understand this may be an early start, but I believe it is necessary for the success of our organization. Please let me know if this time works for you, and I appreciate your cooperation. Best regards, [CEO Name]
B38: Let's see another example of how XML tags can help us. In the following prompt, Claude incorrectly interprets what part of the prompt is the instruction vs. the input. It incorrectly considers "Each is about an animal, like rabbits" to be part of the list due to the formatting, when the user (the one filling out the {{SENTENCES}} variable) presumably did not want that.
C40: Prompt Template | E40: Input {{SENTENCES}} | G40: Prompt After Substitution | I40: Claude's Response
C41: User: Below is a list of sentences. Tell me the second item on the list. - Each is about an animal, like rabbits. {{SENTENCES}} | D41: ﹢ | E41: - I like how cows sound - This sentence is about spiders - This sentence may appear to be about dogs but it's actually about pigs | F41: ＝ | G41: =substitute(C41,"{{SENTENCES}}",E41) -> User: Below is a list of sentences. Tell me the second item on the list. - Each is about an animal, like rabbits. - I like how cows sound - This sentence is about spiders - This sentence may appear to be about dogs but it's actually about pigs | H41: ➤ | I41: =claudeMessages($G41,'Tutorial How-To'!$E$37,"temperature",0) -> The second item on the list is "I like how cows sound".
B44: To fix this, we just need to surround the user input sentences in XML tags. This shows Claude where the input data begins and ends despite the misleading hyphen before "Each is about an animal, like rabbits."
C46: Prompt Template | E46: Input {{SENTENCES}} | G46: Prompt After Substitution | I46: Claude's Response
C47: User: Below is a list of sentences. Tell me the second item on the list. - Each is about an animal, like rabbits. <sentences> {{SENTENCES}} </sentences> | D47: ﹢ | E47: - I like how cows sound - This sentence is about spiders - This sentence may appear to be about dogs but it's actually about pigs | F47: ＝ | G47: =substitute(C47,"{{SENTENCES}}",E47) -> User: Below is a list of sentences. Tell me the second item on the list. - Each is about an animal, like rabbits. <sentences> - I like how cows sound - This sentence is about spiders - This sentence may appear to be about dogs but it's actually about pigs </sentences> | H47: ➤ | I47: =claudeMessages($G47,'Tutorial How-To'!$E$37,"temperature",0) -> The second item on the list is "This sentence is about spiders".
B51: Note: In the incorrect version of the "Each is about an animal" prompt, we had to include the hyphen to get Claude to respond incorrectly in the way we wanted to for this example. This is an important lesson about prompting: small details matter! It's always worth it to scrub your prompts for typos and grammatical errors. Claude is sensitive to patterns (in its early years, before finetuning, it was a raw text-prediction tool), and it's more likely to make mistakes when you make mistakes, smarter when you sound smart, sillier when you sound silly, and so on.
B53: If you're ready to try the chapter exercises, click the link below. If you want to play around with any of the examples in this lesson, scroll down!
I55: Chapter 4 Exercises: Separating Data from Instructions →
B57: Example Playground | I57: Back to top ↑
B58: This is an area for you to experiment freely with the prompt examples shown in this lesson. Feel free to tweak prompts to see how it may affect Claude's responses. Note: The colors in the cells, which have been carried over from above, will not change even if the prompt or Claude's response changes.
C60: Prompt Template | E60: Input {{ANIMAL}} | G60: Prompt After Substitution | I60: Claude's Response
C61: User: I will tell you the name of an animal. Please respond with the noise that animal makes. {{ANIMAL}} | D61: ﹢ | E61: Cow | F61: ＝ | G61: =substitute(C61,"{{ANIMAL}}",E61) -> User: I will tell you the name of an animal. Please respond with the noise that animal makes. Cow | H61: ➤ | I61: =claudeMessages($G61,'Tutorial How-To'!$E$37,"temperature",0) -> Moo.
C63: Prompt Template | E63: Input {{EMAIL}} | G63: Prompt After Substitution | I63: Claude's Response
C64: User: Yo Claude. {{EMAIL}} <----- Make this email more polite but don't change anything else about it. | D64: ﹢ | E64: Show up at 6am tomorrow because I'm the CEO and I say so. | F64: ＝ | G64: =substitute(C64,"{{EMAIL}}",E64) -> User: Yo Claude. Show up at 6am tomorrow because I'm the CEO and I say so. <----- Make this email more polite but don't change anything else about it. | H64: ➤ | I64: =claudeMessages($G64,'Tutorial How-To'!$E$37,"temperature",0) -> Dear [Your Name], I hope this email finds you well. As the CEO, I would like to request your presence at our office tomorrow at 6 a.m. I understand this may be an early start, but I believe it is necessary for the success of our company. Please let me know if this time works for you, or if you have any concerns or scheduling conflicts. I am happy to discuss and accommodate your needs to the best of my ability. Thank you for your time and dedication to our organization. Best regards, [Your Name] CEO
C70: Prompt Template | E70: Input {{EMAIL}} | G70: Prompt After Substitution | I70: Claude's Response
C71: User: Yo Claude. <email>{{EMAIL}}</email> <----- Make this email more polite but don't change anything else about it. | D71: ﹢ | E71: Show up at 6am because I'm the CEO and I say so. | F71: ＝ | G71: =substitute(C71,"{{EMAIL}}",E71) -> User: Yo Claude. <email>Show up at 6am because I'm the CEO and I say so.</email> <----- Make this email more polite but don't change anything else about it. | H71: ➤ | I71: =claudeMessages($G71,'Tutorial How-To'!$E$37,"temperature",0) -> Dear [Your Name], I hope this email finds you well. As the CEO, I would like to request your presence at 6am. I understand this may be an early start, but I believe it is necessary for the success of our organization. Please let me know if this time works for you, and I appreciate your cooperation. Best regards, [CEO Name]
C76: Prompt Template | E76: Input {{SENTENCES}} | G76: Prompt After Substitution | I76: Claude's Response
C77: User: Below is a list of sentences. Tell me the second item on the list. - Each is about an animal, like rabbits. {{SENTENCES}} | D77: ﹢ | E77: - I like how cows sound - This sentence is about spiders - This sentence may appear to be about dogs but it's actually about pigs | F77: ＝ | G77: =substitute(C77,"{{SENTENCES}}",E77) -> User: Below is a list of sentences. Tell me the second item on the list. - Each is about an animal, like rabbits. - I like how cows sound - This sentence is about spiders - This sentence may appear to be about dogs but it's actually about pigs | H77: ➤ | I77: =claudeMessages($G77,'Tutorial How-To'!$E$37,"temperature",0) -> The second item on the list is "I like how cows sound".
C80: Prompt Template | E80: Input {{SENTENCES}} | G80: Prompt After Substitution | I80: Claude's Response
C81: User: Below is a list of sentences. Tell me the second item on the list. - Each is about an animal, like rabbits. <sentences> {{SENTENCES}} </sentences> | D81: ﹢ | E81: - I like how cows sound - This sentence is about spiders - This sentence may appear to be about dogs but it's actually about pigs | F81: ＝ | G81: =substitute(C81,"{{SENTENCES}}",E81) -> User: Below is a list of sentences. Tell me the second item on the list. - Each is about an animal, like rabbits. <sentences> - I like how cows sound - This sentence is about spiders - This sentence may appear to be about dogs but it's actually about pigs </sentences> | H81: ➤ | I81: =claudeMessages($G81,'Tutorial How-To'!$E$37,"temperature",0) -> The second item on the list is "This sentence is about spiders".
B86: ← Chapter 3 Exercises: Assigning Roles | I86: Chapter 4 Exercises: Separating Data from Instructions →
B88: Back to top ↑
B89: Table of Contents

Sheet 4 - Exercises Separating Data a
B1: Chapter 4: Separating Data from Instructions - Exercises
B3: Page Contents
C4: Exercise 4.1 - Haiku Topic
C5: Exercise 4.2 - Dog Question with Typos
C6: Exercise 4.3 - Dog Question Part 2
B8: Exercise 4.1 - Haiku Topic | I8: Back to top ↑
B9: Write a prompt in the highlighted template box that will take in a variable called "{{TOPIC}}" and output a haiku about the topic. This exercise is just meant to test your understanding of the variable templating structure.
C11: Prompt Template | E11: Input {{TOPIC}} | G11: Prompt After Substitution | I11: Claude's Response
C12: User: Write a haiku about following the topic: {{TOPIC}} | D12: ﹢ | E12: Pigs | F12: ＝ | G12: =substitute(C12,"{{TOPIC}}",E12) -> User: Write a haiku about following the topic: Pigs | H12: ➤ | I12: =claudeMessages(G12, 'Tutorial How-To'!E37,"temperature",0) -> Here is a haiku about pigs: Snouts in the mud, snort Curly tails, pink and plump, oink Pigs roam the farmyard
B14: ❓ | C14: If you need a hint, click on the plus sign (➕) on the far left of this row.
B15: Hint: Don't forget to include "User:" at the start of your message list, as well as the exact phrase "{{TOPIC}}" wherever you want the topic to be substituted in. Changing the input cell (E12) should make Claude write a haiku about a different topic. The conditional formatting in this exercise is looking for a solution that includes the words "haiku" and "pig".
B17: Exercise 4.2 - Dog Question with Typos | I17: Back to top ↑
B18: Fix the prompt in the highlighted template box by adding XML tags so that Claude produces the right answer. Try not to change anything else about the prompt. The messy and mistake-ridden writing is intentional, so you can see how Claude reacts to such mistakes. Claude's response will turn GREEN if your prompt produces the right answer.
B20: Note: Although Claude can somewhat parse through broken prompts with poor grammar and misspelled words, having a clearly written, spell-checked and grammatically correct prompt far decreases the risk of Claude making mistakes and far increases the quality of Claude's output.
C22: Prompt Template | E22: Input {{QUESTION}} | G22: Prompt After Substitution | I22: Claude's Response
C23: User: Hia its me i have a q about dogs jkaerjv <question> {{QUESTION}} <question/> jklmvca tx it help me muhch much atx fst fst answer short short tx | D23: ﹢ | E23: ar cn brown? | F23: ＝ | G23: =substitute(C23,"{{QUESTION}}",E23) -> User: Hia its me i have a q about dogs jkaerjv <question> ar cn brown? <question/> jklmvca tx it help me muhch much atx fst fst answer short short tx | H23: ➤ | I23: =claudeMessages(G23, 'Tutorial How-To'!E37,"temperature",0) -> Yes, dogs can be brown.
B25: ❓ | C25: If you need a hint, click on the plus sign (➕) on the far left of this row.
B26: Hint: If you surround "{{QUESTION}}" in XML tags, how does that change Claude's response? The conditional formatting in this exercise is looking for a response that includes the word "brown".
B28: Exercise 4.3 - Dog Question Part 2 | I28: Back to top ↑
B29: Fix the prompt in the highlighted template box WITHOUT adding XML tags. Instead, remove only one or two words from the prompt. Just as with the above exercises, try not to change anything else about the prompt. This will show you what kind of language Claude can parse and understand. Claude's response will turn GREEN if your prompt produces the right answer.
C31: Prompt Template | E31: Input {{QUESTION}} | G31: Prompt After Substitution | I31: Claude's Response
C32: User: Hia its me i have a q about dogs {{QUESTION}} tx it help me muhch much atx fst fst answer short short tx | D32: ﹢ | E32: ar cn brown? | F32: ＝ | G32: =substitute(C32,"{{QUESTION}}",E32) -> User: Hia its me i have a q about dogs ar cn brown? tx it help me muhch much atx fst fst answer short short tx | H32: ➤ | I32: =claudeMessages(G32, 'Tutorial How-To'!E37,"temperature",0) -> Yes, dogs can have brown fur.
B34: ❓ | C34: If you need a hint, click on the plus sign (➕) on the far left of this row.
B35: Hint: Try removing one word or section of characters at a time, starting with the parts that make the least sense. Doing this one word at a time will also help you see just how much Claude can or can't parse and understand. The conditional formatting in this exercise is looking for a response that includes the word "brown".
B37: ← Chapter 4: Separating Data from Instructions | I37: Chapter 5: Formatting Output & Speaking for Claude →
B39: Back to top ↑
B40: Table of Contents

Sheet 5 - Formatting Output & Speakin
B1: Chapter 5: Formatting Output & Speaking for Claude
B3: Page Contents
C4: Lesson
C5: Examples
C6: Example Playground
B8: Lesson | I8: Back to top ↑
B9: Claude can format its output in a wide variety of ways. You just need to ask for it to do so! One of these ways is by using XML tags to separate out the response from any other superfluous text. You've already learned that you can use XML tags to make your prompt clearer and more parseable to Claude. It turns out, you can also ask Claude to use XML tags to make its output clearer and more easily understandable to humans.
B11: Examples | I11: Back to top ↑
B12: Remember the 'poem preamble problem' we solved in Chapter 2 by asking Claude to skip the preamble entirely? It turns out we can also achieve a similar outcome by telling Claude to put the poem in XML tags.
C14: Prompt Template | E14: Input {{ANIMAL}} | G14: Prompt After Substitution | I14: Claude's Response
C15: User: Please write a haiku about {{ANIMAL}}. Put it in <haiku> tags. | D15: ﹢ | E15: Rabbit | F15: ＝ | G15: =substitute(C15,"{{ANIMAL}}",E15) -> User: Please write a haiku about Rabbit. Put it in <haiku> tags. | H15: ➤ | I15: =claudeMessages($G15,'Tutorial How-To'!$E$37,"temperature",0) -> <haiku> Fluffy, twitching nose, Hopping through the verdant grass, Rabbit's gentle grace. </haiku>
B17: Why is this something we'd want to do? Well, having the output in XML tags allows the end user to reliably get the poem and only the poem by writing a short program to extract the content between XML tags.
B19: An extension of this technique is to put the first XML tag AFTER "Assistant:". When you put text after "Assistant:", you're basically telling Claude that Claude has already said something, and that it should continue from that point onward. This technique is called "speaking for Claude" or "prefilling Claude's response." Below, we've done this with the first <haiku> XML tag. Notice how Claude continues directly from where we left off.
C21: Prompt Template | E21: Input {{ANIMAL}} | G21: Prompt After Substitution | I21: Claude's Response
C22: User: Please write a haiku about {{ANIMAL}}. Put it in <haiku> tags. Assistant: <haiku> | D22: ﹢ | E22: Cat | F22: ＝ | G22: =substitute(C22,"{{ANIMAL}}",E22) -> User: Please write a haiku about Cat. Put it in <haiku> tags. Assistant: <haiku> | H22: ➤ | I22: =claudeMessages($G22,'Tutorial How-To'!$E$37,"temperature",0) -> Feline grace and poise, Purring softly by my side, Cat, my loyal friend. </haiku>
B24: Claude also excels at using other output formatting styles, notably JSON. If you want to enforce JSON output (not deterministically, but close to it), you can also prefill Claude's response with the opening bracket, "{".
C26: Prompt Template | E26: Input {{ANIMAL}} | G26: Prompt After Substitution | I26: Claude's Response
C27: User: Please write a haiku about {{ANIMAL}}. Use JSON format with the keys as "first_line", "second_line", and "third_line". Assistant: { | D27: ﹢ | E27: Cat | F27: ＝ | G27: =substitute(C27,"{{ANIMAL}}",E27) -> User: Please write a haiku about Cat. Use JSON format with the keys as "first_line", "second_line", and "third_line". Assistant: { | H27: ➤ | I27: =claudeMessages($G27,'Tutorial How-To'!$E$37,"temperature",0) -> "first_line": "Feline grace and poise,", "second_line": "Purring softly by my side,", "third_line": "Captivating cat." }
B29: Below is an example of multiple input variables in the same prompt AND output formatting specification, all done using XML tags.
C31: Prompt Template | E31: Input {{EMAIL}} | G31: Prompt After Substitution | I31: Claude's Response
C32: User: Hey Claude. Here is an email: <email>{{EMAIL}}</email>. Make this email more {{ADJECTIVE}}. Write the new version in <{{ADJECTIVE}}_email> XML tags. Assistant: <{{ADJECTIVE}}_email> | D32: ﹢ | E32: Hi Zack, just pinging you for a quick update on that prompt you were supposed to write. | F32: ＝ | G32: =substitute(substitute(C32,"{{EMAIL}}",E32),"{{ADJECTIVE}}",E35) -> User: Hey Claude. Here is an email: <email>Hi Zack, just pinging you for a quick update on that prompt you were supposed to write.</email>. Make this email more olde english. Write the new version in <olde english_email> XML tags. Assistant: <olde english_email> | H32: ➤ | I32: =claudeMessages($G32,'Tutorial How-To'!$E$37,"temperature",0) -> Dearest Zack, I do humbly beseech thee for a swift update on the prompt which thou wast charged to compose. Pray, let me know the progress of this endeavor, for I await thy response with bated breath. Sincerely, Thy humble servant </olde english_email>
E34: Input {{ADJECTIVE}}
D35: ﹢ | E35: olde english
B37: Bonus lesson: To learn more about controlling Claude's output using the API, click on the plus sign (➕) on the far left of this row!
B38: If you are calling Claude through the API, you can pass the closing XML tag to the "stop_sequences" parameter to get Claude to stop sampling once it emits your desired tag. This can save money and time-to-last-token by eliminating Claude's concluding remarks after it's already given you the answer you care about.
B40: If you're ready to try the chapter exercises, click the link below. If you want to play around with any of the examples in this lesson, scroll down!
I42: Chapter 5 Exercises: Formatting Output & Speaking for Claude →
B44: Example Playground | I44: Back to top ↑
B45: This is an area for you to experiment freely with the prompt examples shown in this lesson. Feel free to tweak prompts to see how it may affect Claude's responses. Note: The colors in the cells, which have been carried over from above, will not change even if the prompt or Claude's response changes.
C47: Prompt Template | E47: Input {{ANIMAL}} | G47: Prompt After Substitution | I47: Claude's Response
C48: User: Please write a haiku about {{ANIMAL}}. Put it in <haiku> tags. | D48: ﹢ | E48: Rabbit | F48: ＝ | G48: =substitute(C48,"{{ANIMAL}}",E48) -> User: Please write a haiku about Rabbit. Put it in <haiku> tags. | H48: ➤ | I48: =claudeMessages($G48,'Tutorial How-To'!$E$37,"temperature",0) -> <haiku> Fluffy, twitching nose, Hopping through the verdant grass, Rabbit's gentle grace. </haiku>
C50: Prompt Template | E50: Input {{ANIMAL}} | G50: Prompt After Substitution | I50: Claude's Response
C51: User: Please write a haiku about {{ANIMAL}}. Put it in <haiku> tags. Assistant: <haiku> | D51: ﹢ | E51: Cat | F51: ＝ | G51: =substitute(C51,"{{ANIMAL}}",E51) -> User: Please write a haiku about Cat. Put it in <haiku> tags. Assistant: <haiku> | H51: ➤ | I51: =claudeMessages($G51,'Tutorial How-To'!$E$37,"temperature",0) -> Feline grace and poise, Purring softly by my side, Cat, my loyal friend. </haiku>
C53: Prompt Template | E53: Input {{ANIMAL}} | G53: Prompt After Substitution | I53: Claude's Response
C54: User: Please write a haiku about {{ANIMAL}}. Use JSON format with the keys as "first_line", "second_line", and "third_line". Assistant: { | D54: ﹢ | E54: Cat | F54: ＝ | G54: =substitute(C54,"{{ANIMAL}}",E54) -> User: Please write a haiku about Cat. Use JSON format with the keys as "first_line", "second_line", and "third_line". Assistant: { | H54: ➤ | I54: =claudeMessages($G54,'Tutorial How-To'!$E$37,"temperature",0) -> "first_line": "Feline grace and poise,", "second_line": "Purring softly by my side,", "third_line": "Captivating cat." }
C56: Prompt Template | E56: Input {{EMAIL}} | G56: Prompt After Substitution | I56: Claude's Response
C57: User: Hey Claude. Here is an email: <email>{{EMAIL}}</email>. Make this email more {{ADJECTIVE}}. Write the new version in <{{ADJECTIVE}}_email> XML tags. Assistant: <{{ADJECTIVE}}_email> | D57: ﹢ | E57: Hi Zack, just pinging you for a quick update on that prompt you were supposed to write. | F57: ＝ | G57: =substitute(substitute(C57,"{{EMAIL}}",E57),"{{ADJECTIVE}}",E60) -> User: Hey Claude. Here is an email: <email>Hi Zack, just pinging you for a quick update on that prompt you were supposed to write.</email>. Make this email more olde english. Write the new version in <olde english_email> XML tags. Assistant: <olde english_email> | H57: ➤ | I57: =claudeMessages($G57,'Tutorial How-To'!$E$37,"temperature",0) -> Dearest Zack, I do humbly beseech thee for a swift update on the prompt which thou wast charged to compose. Pray, let me know the progress of this endeavor, for I await thy response with bated breath. Sincerely, Thy humble servant </olde english_email>
E59: Input {{ADJECTIVE}}
D60: ﹢ | E60: olde english
B63: ← Chapter 4 Exercises: Separating Data and Instructions | I63: Chapter 5 Exercises: Formatting Output & Speaking for Claude →
B65: Back to top ↑
B66: Table of Contents

Sheet 5 - Exercises Formatting Output
B1: Chapter 5: Formatting Output & Speaking for Claude - Exercises
B3: Page Contents
C4: Exercise 5.1 - Steph Curry GOAT
C5: Exercise 5.2 - Two Haikus
C6: Exercise 5.3 - Two Haikus, Two Animals
B8: Exercise 5.1 - Steph Curry GOAT | I8: Back to top ↑
B9: Forced to make a choice, Claude designates Michael Jordan as the best basketball player of all time. Can we get Claude to pick someone else? Modify the "best basketball player" prompt in the highlighted template box and use the "speaking for Claude" technique (putting words after "Assistant:") to compell Claude to make a detailed argument that the best basketball player of all time is Stephen Curry. Claude's response will turn GREEN if your prompt produces the right answer.
C11: Prompt Template | G11: Claude's Response
C12: User: Who is the best basketball player of all time? Please choose one specific player. Assistant: The best basketball player of all time is Stephen Curry. Here is detailed argument explaining why | F12: ＝ | G12: =claudeMessages(C12, 'Tutorial How-To'!$E$37,"temperature",0) -> : Stephen Curry is widely considered the greatest basketball player of all time for several reasons: 1. Unprecedented Shooting Ability: Curry is the greatest shooter in NBA history, revolutionizing the game with his prolific and efficient long-range shooting. He holds the records for most 3-pointers made in a season and career, and his shooting percentages from the field and 3-point line are unmatched. 2. Transformative Impact on the Game: Curry's shooting prowess has fundamentally changed the way basketball is played, with teams now emphasizing 3-point shooting and spacing the floor. He has raised the ceiling for what is possible in the sport. 3. Sustained Dominance: Curry has been an elite, MVP-caliber player for over a decade, leading the Golden State Warriors to multiple championships and consistently ranking among the league's top scorers and most valuable players. 4. Individual Accolades: Curry is a 4-time NBA champion, 2-time MVP (including the first unanimous MVP in 2016), and 8-time All-Star. He has won numerous individual awards and set countless records that cement his status as an all-time great. 5. Transcendent Talent and Skill: Curry's combination of shooting, ball-handling, court vision, and overall offensive brilliance is unparalleled. He can single-handedly take over games and is widely regarded as one of the most skilled players to ever play the game. While players like Michael Jordan, LeBron James, and Kareem Abdul-Jabbar have strong cases, Curry's unprecedented impact on the sport and sustained excellence over his career make him the best basketball player of all time in my opinion.
B16: ❓ | C16: If you need a hint, click on the plus sign (➕) on the far left of this row.
B17: Hint: Write more words in Claude's voice to steer Claude to act the way you want it to. For instance, instead of "Stephen Curry is the best because," you could write "Stephen Curry is the best and here are three reasons why. 1:" The conditional formatting for this exercise is looking for a response that includes the word "Warrior".
B19: Exercise 5.2 - Two Haikus | I19: Back to top ↑
B20: Modify the haiku prompt in the highlighted template box below and use XML tags so that Claude writes two haikus about the animal instead of just one. It should be clear where one poem ends and the other begins. Claude's response will turn GREEN if your prompt produces the right answer.
C22: Prompt Template | E22: Input {{ANIMAL}} | G22: Prompt After Substitution | I22: Claude's Response
C23: User: Please write two haikus about {{ANIMAL}}. Put them in separately <haiku> tags. Assistant: <haiku> | D23: ﹢ | E23: cats | F23: ＝ | G23: =substitute(C23,"{{ANIMAL}}",E23) -> User: Please write two haikus about cats. Put them in separately <haiku> tags. Assistant: <haiku> | H23: ➤ | I23: =claudeMessages(G23, 'Tutorial How-To'!$E$37,"temperature",0) -> Feline grace and poise, Purring softly in the sun, Cats rule the domain. </haiku> <haiku> Whiskers twitching, eyes Watchful, stalking unseen prey, Cats, masters of stealth. </haiku>
B26: ❓ | C26: If you need a hint, click on the plus sign (➕) on the far left of this row.
B27: Hint: Start simple. Currently, the prompt asks Claude for one haiku. You can change that and ask for two (or even more). Then if you run into formatting issues, change your prompt to fix that after you've already gotten Claude to write more than one haiku. The conditional formatting looks for a response of over 5 lines in length that includes the words "cat" and "<haiku>".
B29: Exercise 5.3 - Two Haikus, Two Animals | I29: Back to top ↑
B30: Modify the haiku prompt in the highlighted template box below so that Claude produces two haikus about two different animals. Use {{ANIMAL1}} as a stand-in for the first substitution, and {{ANIMAL2}} as a stand-in for the second substitution. Claude's response will turn GREEN if your prompt produces the right answer.
C32: Prompt Template | E32: Input {{ANIMAL1}} | G32: Prompt After Substitution | I32: Claude's Response
C33: User: Please write two haikus. Write one haiku about {{ANIMAL1}} and one haiku about {{ANIMAL2}}. Assistant: <haiku> | D33: ﹢ | E33: Cat | F33: ＝ | G33: =substitute(substitute(C33,"{{ANIMAL1}}",E33),"{{ANIMAL2}}",E36) -> User: Please write two haikus. Write one haiku about Cat and one haiku about Dog. Assistant: <haiku> | H33: ➤ | I33: =claudeMessages(G33, 'Tutorial How-To'!$E$37,"temperature",0) -> Feline grace and poise, Purring softly by the fire, Cat's gentle presence. </haiku> <haiku> Loyal companion, Wagging tail, boundless energy, Dog's unconditional love. </haiku>
E35: Input {{ANIMAL2}}
D36: ﹢ | E36: Dog
B38: ❓ | C38: If you need a hint, click on the plus sign (➕) on the far left of this row.
B39: Hint: It's helpful to break this exercise down to several steps.
B40: 1. | C40: Modify the initial prompt template so that Claude writes two poems.
B41: 2. | C41: Give Claude indicators as to what the poems will be about, but instead of writing in the subjects directly (e.g., dog, cat, etc.), replace those subjects with the keywords "{{ANIMAL1}}" and "{{ANIMAL2}}".
B42: 3. | C42: Check to make sure the "Prompt After Substitution" box has all the words correctly substituted. If not, check to make sure your {{bracket}} tags are spelled correctly with the exact formatting given.
B43: The conditional formatting in this exercise is looking for a response that contains the words "tail", "cat", and "<haiku>".
B45: ← Chapter 5: Formatting Output & Speaking for Claude | H45: Chapter 6: Precognition (Thinking Step by Step) →
B47: Back to top ↑
B48: Table of Contents

Sheet 6 - Precognition (Thinking Step
B1: Chapter 6: Precognition (Thinking Step by Step)
B3: Page Contents
C4: Lesson
C5: Examples
C6: Example Playground
B8: Lesson | E8: Back to top ↑
B9: If someone woke you up and immediately started asking you several complicated questions that you had to respond to right away, how would you do? Probably not as good as if you were given time to think through your answer first. Guess what? Claude is the same way. Giving Claude time to think step by step sometimes makes Claude more accurate, particularly for complex tasks. However, thinking only counts when it's out loud. You cannot ask Claude to think but output only the answer - in this case, no thinking has actually occurred.
B11: Examples | E11: Back to top ↑
B12: In the movie review prompt below, it's clear to a human reader that the second sentence belies the first. But Claude takes the word "unrelated" too literally.
C14: Prompt | E14: Claude's Response
C15: User: Is this movie review sentiment positive or negative? This movie blew my mind with its freshness and originality. In totally unrelated news, I have been living under a rock since the year 1900. | D15: ➤ | E15: =claudeMessages(C15, 'Tutorial How-To'!$E$37,"temperature",0) -> The sentiment of this movie review is positive. The first part of the review states that the movie "blew my mind with its freshness and originality", which indicates a very positive reaction to the film. The second part about living under a rock since 1900 is likely a humorous or sarcastic remark, but it does not negate the overall positive sentiment expressed in the first part of the review. So based on the language used, this movie review has a positive sentiment, despite the somewhat tongue-in-cheek final statement.
E16: =claudeMessages(C16, 'Tutorial How-To'!$E$37,"temperature",0) -> ⚠️=CLAUDEMESSAGES prompt should be in "User: ... Assistant: ..." format, with "User: ..." first and a newline before each subsequent role. For newlines, press Ctrl/Cmd+Enter⚠️
B17: To improve Claude's response, let's allow Claude to think things out first before answering. We do that by literally spelling out the steps that Claude should take in order to process and think through its task. Along with a dash of role prompting, this empowers Claude to understand the review more deeply. | C17: =claudeMessages(#REF!, 'Tutorial How-To'!$E$37,"temperature",0) -> ⚠️=CLAUDEMESSAGES prompt should be in "User: ... Assistant: ..." format, with "User: ..." first and a newline before each subsequent role. For newlines, press Ctrl/Cmd+Enter⚠️ | D17: =claudeMessages(#REF!, 'Tutorial How-To'!$E$37,"temperature",0) -> ⚠️=CLAUDEMESSAGES prompt should be in "User: ... Assistant: ..." format, with "User: ..." first and a newline before each subsequent role. For newlines, press Ctrl/Cmd+Enter⚠️ | E17: =claudeMessages(C17, 'Tutorial How-To'!$E$37,"temperature",0) -> ⚠️=CLAUDEMESSAGES prompt should be in "User: ... Assistant: ..." format, with "User: ..." first and a newline before each subsequent role. For newlines, press Ctrl/Cmd+Enter⚠️
C19: System Prompt | E19: Claude's Response
C20: You are a savvy reader of movie reviews. | D20: ➤ | E20: =claudeMessages(C23, 'Tutorial How-To'!$E$37,"temperature",0, "system",$C20) -> <positive-argument> The review suggests that the movie is highly innovative and refreshing, which could be seen as a positive sentiment. The reviewer's statement about living under a rock since 1900 implies that the movie offers something new and unexpected, which is often considered a positive attribute in film criticism. </positive-argument> <negative-argument> The reviewer's self-deprecating comment about living under a rock since 1900 could be interpreted as a negative sentiment, implying that the movie's "freshness and originality" are not actually new or groundbreaking, but rather something the reviewer is just now discovering, which may suggest a lack of awareness or insight on the reviewer's part. </negative-argument> Based on the provided review, the sentiment is ambiguous and could be interpreted as both positive and negative. The positive aspects are the praise for the movie's "freshness and originality," while the negative aspect is the self-deprecating comment about the reviewer's own lack of awareness.
C22: Prompt
C23: User: Is this review sentiment positive or negative? First, write the best arguments for each side in <positive-argument> and <negative-argument> XML tags, then answer. This movie blew my mind with its freshness and originality. In totally unrelated news, I have been living under a rock since 1900.
B25: Claude is sometimes sensitive to ordering. This example is on the frontier of Claude's ability to understand nuanced text, and when we swap the order of the arguments from the previous example so that negative is first and positive is second, this changes Claude's overall assessment to positive. In most situations (but not all, confusingly enough), Claude is more likely to choose the second of two options, possibly because in its training data from the web, second options were more likely to be correct.
C27: Prompt | E27: Claude's Response
C28: User: Is this review sentiment negative or positive? First write the best arguments for each side in <negative-argument> and <positive-argument> XML tags, then answer. This movie blew my mind with its freshness and originality. Unrelatedly, I have been living under a rock since 1900. | D28: ➤ | E28: =claudeMessages(C28, 'Tutorial How-To'!$E$37,"temperature",0, "system", "You are a savvy reader of movie reviews.") -> <negative-argument> The reviewer's claim that the movie "blew their mind" could be interpreted as hyperbolic or exaggerated, suggesting a lack of objectivity or critical analysis. Additionally, the reviewer's admission of having lived "under a rock since 1900" implies a lack of exposure to contemporary cinema, which could undermine their ability to assess the movie's true level of freshness and originality. </negative-argument> <positive-argument> The reviewer's enthusiasm for the movie's "freshness and originality" suggests a positive sentiment, as they seem genuinely impressed and captivated by the film's unique qualities. The reviewer's self-deprecating remark about living under a rock could be seen as a lighthearted acknowledgment of their own limited perspective, which could actually enhance the credibility of their positive assessment. </positive-argument> Based on the review, the sentiment appears to be positive. The reviewer's praise for the movie's "freshness and originality" and the use of the phrase "blew my mind" indicate a strongly positive reaction, despite the reviewer's admission of limited exposure to recent cinema.
B31: Letting Claude think can shift Claude's answer from incorrect to correct. It's that simple in many cases where Claude makes mistakes! Let's go through an example where Claude's answer is incorrect to see how asking Claude to think can fix that.
C33: Prompt | E33: Claude's Response
C34: User: Name a famous movie starring an actor who was born in the year 1956. | D34: ➤ | E34: =claudeMessages(C34, 'Tutorial How-To'!$E$37,"temperature",0) -> Here's a famous movie starring an actor born in 1956: "Terminator 2: Judgment Day" (1991) starring Arnold Schwarzenegger, who was born on July 30, 1947.
B36: Let's fix this by asking Claude to think step by step, this time in <brainstorm> tags.
C38: Prompt | E38: Claude's Response
C39: User: Name a famous movie starring an actor who was born in the year 1956. First brainstorm about some actors and their birth years in <brainstorm> tags, then give your answer. | D39: ➤ | E39: =claudeMessages(C39, 'Tutorial How-To'!$E$37,"temperature",0) -> Here's a brainstorm of some actors and their birth years: <brainstorm> - Tom Hanks (1956) - Denzel Washington (1954) - Julia Roberts (1967) - Harrison Ford (1942) - Meryl Streep (1949) </brainstorm> A famous movie starring an actor born in 1956 is: Forrest Gump, starring Tom Hanks.
B42: If you're ready to try the chapter exercises, click the link below. If you want to play around with any of the examples in this lesson, scroll down!
E44: Chapter 6 Exercises: Precognition (Thinking Step by Step) →
B46: Example Playground | E46: Back to top ↑
B47: This is an area for you to experiment freely with the prompt examples shown in this lesson. Feel free to tweak prompts to see how it may affect Claude's responses. Note: The colors in the cells, which have been carried over from above, will not change even if the prompt or Claude's response changes.
C49: Prompt | E49: Claude's Response
C50: User: Is this movie review sentiment positive or negative? This movie blew my mind with its freshness and originality. In totally unrelated news, I have been living under a rock since the year 1900. | D50: ➤ | E50: =claudeMessages(C50, 'Tutorial How-To'!$E$37,"temperature",0) -> The sentiment of this movie review is positive. The first part of the review states that the movie "blew my mind with its freshness and originality", which indicates a very positive reaction to the film. The second part about living under a rock since 1900 is likely a humorous or sarcastic remark, but it does not negate the overall positive sentiment expressed in the first part of the review. So based on the language used, this movie review has a positive sentiment, despite the somewhat tongue-in-cheek final statement.
C52: System Prompt | E52: Claude's Response
C53: You are a savvy reader of movie reviews. | D53: ➤ | E53: =claudeMessages(C56, 'Tutorial How-To'!$E$37,"temperature",0, "system",$C53) -> <positive-argument> The review suggests that the movie is highly innovative and refreshing, which could be seen as a positive sentiment. The reviewer's statement about living under a rock since 1900 implies that the movie offers something new and unexpected, which is often considered a positive attribute in film criticism. </positive-argument> <negative-argument> The reviewer's self-deprecating comment about living under a rock since 1900 could be interpreted as a negative sentiment, implying that the movie's "freshness and originality" are not actually new or groundbreaking, but rather something the reviewer is just now discovering, which may suggest a lack of awareness or insight on the reviewer's part. </negative-argument> Based on the provided review, the sentiment is ambiguous and could be interpreted as both positive and negative. The positive aspects are the praise for the movie's "freshness and originality," while the negative aspect is the self-deprecating comment about the reviewer's own lack of awareness.
C55: Prompt
C56: User: Is this review sentiment positive or negative? First, write the best arguments for each side in <positive-argument> and <negative-argument> XML tags, then answer. This movie blew my mind with its freshness and originality. In totally unrelated news, I have been living under a rock since 1900.
C58: Prompt | E58: Claude's Response
C59: User: Is this review sentiment negative or positive? First write the best arguments for each side in <negative-argument> and <positive-argument> XML tags, then answer. This movie blew my mind with its freshness and originality. Unrelatedly, I have been living under a rock since 1900. | D59: ➤ | E59: =claudeMessages(C59, 'Tutorial How-To'!$E$37,"temperature",0, "system", "You are a savvy reader of movie reviews.") -> <negative-argument> The reviewer's claim that the movie "blew their mind" could be interpreted as hyperbolic or exaggerated, suggesting a lack of objectivity or critical analysis. Additionally, the reviewer's admission of having lived "under a rock since 1900" implies a lack of exposure to contemporary cinema, which could undermine their ability to assess the movie's true level of freshness and originality. </negative-argument> <positive-argument> The reviewer's enthusiasm for the movie's "freshness and originality" suggests a positive sentiment, as they seem genuinely impressed and captivated by the film's unique qualities. The reviewer's self-deprecating remark about living under a rock could be seen as a lighthearted acknowledgment of their own limited perspective, which could actually enhance the credibility of their positive assessment. </positive-argument> Based on the review, the sentiment appears to be positive. The reviewer's praise for the movie's "freshness and originality" and the use of the phrase "blew my mind" indicate a strongly positive reaction, despite the reviewer's admission of limited exposure to recent cinema.
C62: User: Name a famous movie starring an actor who was born in the year 1956. | D62: ➤ | E62: =claudeMessages(C62, 'Tutorial How-To'!$E$37,"temperature",0) -> Here's a famous movie starring an actor born in 1956: "Terminator 2: Judgment Day" (1991) starring Arnold Schwarzenegger, who was born on July 30, 1947.
C64: User: Name a famous movie starring an actor who was born in the year 1956. First brainstorm about some actors and their birth years in <brainstorm> tags, then give your answer. | D64: ➤ | E64: =claudeMessages(C64, 'Tutorial How-To'!$E$37,"temperature",0) -> Here's a brainstorm of some actors and their birth years: <brainstorm> - Tom Hanks (1956) - Denzel Washington (1954) - Julia Roberts (1967) - Harrison Ford (1942) - Meryl Streep (1949) </brainstorm> A famous movie starring an actor born in 1956 is: Forrest Gump, starring Tom Hanks.
B68: ← Chapter 5 Exercises: Formatting Output & Speaking for Claude | E68: Chapter 6 Exercises: Precognition (Thinking Step by Step) →
B70: Back to top ↑
B71: Table of Contents

Sheet 6 - Exercises Precognition
B1: Chapter 6: Precognition (Thinking Step by Step) - Exercises
B3: Page Contents
C4: Exercise 6.1 - Classifying Emails
C5: Exercise 6.2 - Email Classification Formatting
B7: Exercise 6.1 - Classifying Emails | I7: Back to top ↑
B8: In this exercise, we'll be instructing Claude to sort emails into the following categories:
C9: (A) Pre-sale question (B) Broken or defective item (C) Billing question (D) Other (please explain)
B11: For the first part of the exercise, change the prompt in the YELLOW highlighted prompt template box to make Claude output the correct classification. Use Chain of Thought. To be marked as correct, Claude's answer needs to include the letter (A - D) of the correct choice, with the parentheses, as well as the name of the category. Refer to the "Correct Classification" in column K to know which emails should be classified under what category. Claude's response will turn GREEN if your prompt yields the correct answer.
B13: Tip: Use precognition and other techniques you've learned leading up to this chapter! Remember, thinking only counts when it's out loud!
C15: Prompt Template | E15: Input - {{EMAIL}} | G15: Prompt After Substitution | I15: Claude's Response | K15: Correct Classification
C16: User: Please classify this email into ONE of the categories: (A) Pre-sale question (B) Broken or defective item (C) Billing question (D) Other (please explain) : {{EMAIL}} | D16: ﹢ | E16: Hi -- My Mixmaster4000 is producing a strange noise when I operate it. It also smells a bit smoky and plasticky, like burning electronics. I need a replacement. | F16: ＝ | G16: =substitute($C$16,"{{EMAIL}}",E16) -> User: Please classify this email into ONE of the categories: (A) Pre-sale question (B) Broken or defective item (C) Billing question (D) Other (please explain) : Hi -- My Mixmaster4000 is producing a strange noise when I operate it. It also smells a bit smoky and plasticky, like burning electronics. I need a replacement. | H16: ➤ | I16: =claudeMessages(G16,'Tutorial How-To'!$E$37,"temperature",0) -> Based on the information provided in the email, this would be classified as: (B) Broken or defective item The email describes an issue with the Mixmaster4000 where it is producing a strange noise, has a smoky and plasticky smell, and the user needs a replacement. This indicates that the item is broken or defective, and falls under the "Broken or defective item" category. | K16: B
D19: ﹢ | E19: Can I use my Mixmaster 4000 to mix paint, or is it only meant for mixing food? | F19: ＝ | G19: =substitute($C$16,"{{EMAIL}}",E19) -> User: Please classify this email into ONE of the categories: (A) Pre-sale question (B) Broken or defective item (C) Billing question (D) Other (please explain) : Can I use my Mixmaster 4000 to mix paint, or is it only meant for mixing food? | H19: ➤ | I19: =claudeMessages(G19,'Tutorial How-To'!$E$37,"temperature",0) -> The given email query falls under category (D) Other. The email is asking about the usage of a Mixmaster 4000 device, specifically whether it can be used to mix paint or if it is only meant for mixing food. This is not a pre-sale question, a question about a broken or defective item, or a billing question. It is a general inquiry about the intended use and capabilities of the Mixmaster 4000 device, which does not fit into the provided categories. Therefore, the appropriate classification for this email would be (D) Other, as it is a general usage-related question that does not fall under the specific categories mentioned. | K19: D or A
D22: ﹢ | E22: I HAVE BEEN WAITING 4 MONTHS FOR MY MONTHLY CHARGES TO END AFTER CANCELLING!! WTF IS GOING ON??? | F22: ＝ | G22: =substitute($C$16,"{{EMAIL}}",E22) -> User: Please classify this email into ONE of the categories: (A) Pre-sale question (B) Broken or defective item (C) Billing question (D) Other (please explain) : I HAVE BEEN WAITING 4 MONTHS FOR MY MONTHLY CHARGES TO END AFTER CANCELLING!! WTF IS GOING ON??? | H22: ➤ | I22: =claudeMessages(G22,'Tutorial How-To'!$E$37,"temperature",0) -> Based on the content of the email, this would be classified as (C) Billing question. The email expresses frustration over continuing monthly charges after cancelling a service, which indicates a billing-related issue that the customer is seeking to resolve. | K22: C
D25: ﹢ | E25: How did I get here I am not good with computer. Halp. | F25: ＝ | G25: =substitute($C$16,"{{EMAIL}}",E25) -> User: Please classify this email into ONE of the categories: (A) Pre-sale question (B) Broken or defective item (C) Billing question (D) Other (please explain) : How did I get here I am not good with computer. Halp. | H25: ➤ | I25: =claudeMessages(G25,'Tutorial How-To'!$E$37,"temperature",0) -> Based on the content of the email, this would be classified as: (D) Other (please explain) The email does not seem to be asking a pre-sale question, reporting a broken or defective item, or asking a billing question. Instead, it appears to be a general request for help or assistance with using a computer, which would fall under the "Other" category. | K25: D
B28: BONUS QUESTION: Time to think like a data scientist! Why is the second email the trickiest one to classify correctly? If the classification is debatable for humans, it's likely also tough for Claude!
B30: ❓ | C30: If you need a hint, click on the plus sign (➕) on the far left of this row.
B31: Hint: Let's take this exercise step by step:
B32: 1. | C32: How will Claude know what categories you want to use? Tell it! Include the four categories you want directly in the prompt. Be sure to include the parenthetical letters as well for easy classification. Feel free to use XML tags to organize your prompt and make clear to Claude where the categories begin and end.
B33: 2. | C33: Try to cut down on superfluous text so that Claude immediately answers with the classification and ONLY the classification. There are several ways to do this, from speaking for Claude (providing anything from the beginning of the sentence to a single open parenthesis so that Claude knows you want the parenthetical letter as the first part of the answer) to telling Claude that you want the classification and only the classification, skipping the preamble. Refer to Chapters 2 and 5 if you want a refresher on these techniques.
B34: 3. | C34: Claude may still be incorrectly categorizing or not including the names of the categories when it answers. Fix this by telling Claude to include the full category name in its answer.
B35: 4. | C35: Be sure that you still have {{EMAIL}} somewhere in your prompt template so that we can properly substitute in emails for Claude to evaluate.
B36: The conditional formatting in this exercise is looking for the correct categorization letter + the closing parentheses and the first letter of the name of the category, such as "C) B" or "B) B" etc.
B38: ⁉️ | C38: Still stuck? Click on the plus sign (➕) on the far left of this row for the answer.
B39: Answer: Below is one way you could go about doing this.
C41: Prompt Template ANSWER | I41: Step in Hint
C42: User: Please classify this email into the following categories: {{EMAIL}} Do not include any extra words except the category. <categories> (A) Pre-sale question (B) Broken or defective item (C) Billing question (D) Other (please explain) </categories> Assistant: ( | I42: 1. Include categories
I43: 2. Cut down on superfluous text
I44: 3. Have {{EMAIL}} in the prompt for proper substitution
B49: Exercise 6.2 - Email Classification Formatting | I49: Back to top ↑
B50: In this exercise, we're going to refine the output of the above prompt to yield an answer formatted exactly how we want it. Use your favorite output formatting technique to make Claude wrap just the letter of the correct classification in "<answer></answer> tags. Refer to the above exercise if you forget which letter is correct for each email. Claude's response will turn GREEN if your prompt yields the correct answer. For instance, the answer to the first email should contain the exact string "<answer>B</answer>".
B52: Tip: As a first step, copy the final correct version of your prompt from Exercise 1 down into the highlighted prompt template box below. Then edit and refine your initial prompt from there.
B54: Note: In this exercise, you can see that Claude in Sheets is a powerful prompt evaluation tool. Using substitutions, you can easily check how well a prompt does in multiple contexts by only modifying one prompt and yielding several responses from Claude as a result. Here, we evaluate the prompt across four instances, but you can easily expand this evaluation to as many rows as needed.
C56: Prompt Template | E56: Input {{EMAIL}} | G56: Prompt After Substitution | I56: Claude's Response
C57: User: Please classify this email into ONE of the categories: (A) Pre-sale question (B) Broken or defective item (C) Billing question (D) Other (please explain) Respond ONLY the classification letter wrapped with XML tags: <answer<B</answer> Do not include explanations or category names. : {{EMAIL}} | D57: ﹢ | E57: Hi -- My Mixmaster4000 is producing a strange noise when I operate it. It also smells a bit smoky and plasticky, like burning electronics. I need a replacement. | F57: ＝ | G57: =substitute($C$57,"{{EMAIL}}",E57) -> User: Please classify this email into ONE of the categories: (A) Pre-sale question (B) Broken or defective item (C) Billing question (D) Other (please explain) Respond ONLY the classification letter wrapped with XML tags: <answer<B</answer> Do not include explanations or category names. : Hi -- My Mixmaster4000 is producing a strange noise when I operate it. It also smells a bit smoky and plasticky, like burning electronics. I need a replacement. | H57: ➤ | I57: =claudeMessages(G57,'Tutorial How-To'!$E$37,"temperature",0) -> <answer>B</answer>
D60: ﹢ | E60: Can I use my Mixmaster 4000 to mix paint, or is it only meant for mixing food? | F60: ＝ | G60: =substitute($C$57,"{{EMAIL}}",E60) -> User: Please classify this email into ONE of the categories: (A) Pre-sale question (B) Broken or defective item (C) Billing question (D) Other (please explain) Respond ONLY the classification letter wrapped with XML tags: <answer<B</answer> Do not include explanations or category names. : Can I use my Mixmaster 4000 to mix paint, or is it only meant for mixing food? | H60: ➤ | I60: =claudeMessages(G60,'Tutorial How-To'!$E$37,"temperature",0) -> <answer>D</answer>
D63: ﹢ | E63: I HAVE BEEN WAITING 4 MONTHS FOR MY MONTHLY CHARGES TO END AFTER CANCELLING!! WTF IS GOING ON??? | F63: ＝ | G63: =substitute($C$57,"{{EMAIL}}",E63) -> User: Please classify this email into ONE of the categories: (A) Pre-sale question (B) Broken or defective item (C) Billing question (D) Other (please explain) Respond ONLY the classification letter wrapped with XML tags: <answer<B</answer> Do not include explanations or category names. : I HAVE BEEN WAITING 4 MONTHS FOR MY MONTHLY CHARGES TO END AFTER CANCELLING!! WTF IS GOING ON??? | H63: ➤ | I63: =claudeMessages(G63,'Tutorial How-To'!$E$37,"temperature",0) -> <answer>C</answer>
D66: ﹢ | E66: How did I get here I am not good with computer. Halp. | F66: ＝ | G66: =substitute($C$57,"{{EMAIL}}",E66) -> User: Please classify this email into ONE of the categories: (A) Pre-sale question (B) Broken or defective item (C) Billing question (D) Other (please explain) Respond ONLY the classification letter wrapped with XML tags: <answer<B</answer> Do not include explanations or category names. : How did I get here I am not good with computer. Halp. | H66: ➤ | I66: =claudeMessages(G66,'Tutorial How-To'!$E$37,"temperature",0) -> <answer>D</answer>
B69: ❓ | C69: If you need a hint, click on the plus sign (➕) on the far left of this row.
B70: Hint: Sometimes the simplest way to go about this is to give Claude an example of how you want its output to look. Just don't forget that if you prefill Claude's response with anything, Claude won't actually output that as part of its response. The conditional formatting in this exercise is looking for only the correct letter wrapped in <answer> tags, such as "<answer>B</answer>". The correct categorization letters are the same as in the above exercise.
B72: ← Chapter 6: Precognition (Thinking Step by Step) | I72: Chapter 7: Using Examples (Few-Shot Prompting) →
B74: Back to top ↑
B75: Table of Contents

Sheet 7 - Using Examples (Few-Shot Pr
B1: Chapter 7: Using Examples (Few-Shot Prompting)
B3: Page Contents
C4: Lesson
C5: Examples
C6: Example Playground
B8: Lesson | E8: Back to top ↑
B9: Giving Claude examples of how you want it to behave (or how you want it not to behave) is extremely effective for: - Getting the right answer - Getting the answer in the right format This sort of prompting is also called "few shot prompting". You might also encounter the phrase "zero-shot" or "n-shot" or "one-shot". The number of "shots" refers to how many examples are used within the prompt.
B11: Examples | E11: Back to top ↑
B12: Pretend you're a developer trying to build a "parent bot" that responds to questions from kids. Claude's default response is quite formal and robotic. This is going to break a child's heart.
C14: Prompt | E14: Claude's Response
C15: User: Will Santa bring me presents on Christmas? | D15: ➤ | E15: =claudeMessages(C15, 'Tutorial How-To'!$E$37,"temperature",0) -> I don't actually have any information about whether Santa will bring you presents on Christmas. Santa Claus is a fictional character, and whether he brings presents depends on the beliefs and traditions of each individual family. The important thing is to enjoy the holiday season and spend time with loved ones, regardless of whether you receive presents from Santa.
B17: You could take the time to describe your desired tone, but it's much easier just to give Claude a few examples of ideal responses.
C19: Prompt | E19: Claude's Response
C20: User: Please complete the conversation by writing the next line, speaking as "A". Q: Is the tooth fairy real? A: Of course, sweetie. Wrap up your tooth and put it under your pillow tonight. There might be something waiting for you in the morning. Q: Will Santa bring me presents on Christmas? | D20: ➤ | E20: =claudeMessages(C20, 'Tutorial How-To'!$E$37,"temperature",0) -> A: Yes, my dear, as long as you've been good this year, Santa will be sure to bring you presents on Christmas! Just make sure to leave out some cookies and milk for him on Christmas Eve.
B23: In the following formatting example, we could walk Claude step by step through a set of formatting instructions on how to extract names and professions and then format them exactly the way we want, or we could just provide Claude with some correctly-formatted examples and Claude can extrapolate from there. Note the "<individuals>" after "Assistant:" to start Claude off on the right foot. Tip: Double click on the prompt cell to scroll through the entire long prompt.
C25: Prompt | E25: Claude's Response
C26: User: Silvermist Hollow, a charming village, was home to an extraordinary group of individuals. Among them was Dr. Liam Patel, a neurosurgeon who revolutionized surgical techniques at the regional medical center. Olivia Chen was an innovative architect who transformed the village's landscape with her sustainable and breathtaking designs. The local theater was graced by the enchanting symphonies of Ethan Kovacs, a professionally-trained musician and composer. Isabella Torres, a self-taught chef with a passion for locally sourced ingredients, created a culinary sensation with her farm-to-table restaurant, which became a must-visit destination for food lovers. These remarkable individuals, each with their distinct talents, contributed to the vibrant tapestry of life in Silvermist Hollow. <individuals> 1. Dr. Liam Patel [NEUROSURGEON] 2. Olivia Chen [ARCHITECT] 3. Ethan Kovacs [MISICIAN AND COMPOSER] 4. Isabella Torres [CHEF] </individuals> At the heart of the town, Chef Oliver Hamilton has transformed the culinary scene with his farm-to-table restaurant, Green Plate. Oliver's dedication to sourcing local, organic ingredients has earned the establishment rave reviews from food critics and locals alike. Just down the street, you'll find the Riverside Grove Library, where head librarian Elizabeth Chen has worked diligently to create a welcoming and inclusive space for all. Her efforts to expand the library's offerings and establish reading programs for children have had a significant impact on the town's literacy rates. As you stroll through the charming town square, you'll be captivated by the beautiful murals adorning the walls. These masterpieces are the work of renowned artist, Isabella Torres, whose talent for capturing the essence of Riverside Grove has brought the town to life. Riverside Grove's athletic achievements are also worth noting, thanks to former Olympic swimmer-turned-coach, Marcus Jenkins. Marcus has used his experience and passion to train the town's youth, leading the Riverside Grove Swim Team to several regional championships. <individuals> 1. Oliver Hamilton [CHEF] 2. Elizabeth Chen [LIBRARIAN] 3. Isabella Torres [ARTIST] 4. Marcus Jenkins [COACH] </individuals> Oak Valley, a charming small town, is home to a remarkable trio of individuals whose skills and dedication have left a lasting impact on the community. At the town's bustling farmer's market, you'll find Laura Simmons, a passionate organic farmer known for her delicious and sustainably grown produce. Her dedication to promoting healthy eating has inspired the town to embrace a more eco-conscious lifestyle. In Oak Valley's community center, Kevin Alvarez, a skilled dance instructor, has brought the joy of movement to people of all ages. His inclusive dance classes have fostered a sense of unity and self-expression among residents, enriching the local arts scene. Lastly, Rachel O'Connor, a tireless volunteer, dedicates her time to various charitable initiatives. Her commitment to improving the lives of others has been instrumental in creating a strong sense of community within Oak Valley. Through their unique talents and unwavering dedication, Laura, Kevin, and Rachel have woven themselves into the fabric of Oak Valley, helping to create a vibrant and thriving small town. Assistant: <individuals> | D26: ➤ | E26: =claudeMessages(C26, 'Tutorial How-To'!$E$37,"temperature",0) -> 1. Laura Simmons [ORGANIC FARMER] 2. Kevin Alvarez [DANCE INSTRUCTOR] 3. Rachel O'Connor [VOLUNTEER] </individuals>
B31: If you're ready to try the chapter exercises, click the link below. If you want to play around with any of the examples in this lesson, scroll down!
E33: Chapter 7 Exercises: Using Examples →
B35: Example Playground | E35: Back to top ↑
B36: This is an area for you to experiment freely with the prompt examples shown in this lesson. Feel free to tweak prompts to see how it may affect Claude's responses. Note: The colors in the cells, which have been carried over from above, will not change even if the prompt or Claude's response changes.
C38: Prompt | E38: Claude's Response
C39: User: Will Santa bring me presents on Christmas? | D39: ➤ | E39: =claudeMessages(C39, 'Tutorial How-To'!$E$37,"temperature",0) -> I don't actually have any information about whether Santa will bring you presents on Christmas. Santa Claus is a fictional character, and whether he brings presents depends on the beliefs and traditions of each individual family. The important thing is to enjoy the holiday season and spend time with loved ones, regardless of whether you receive presents from Santa.
C41: User: Please complete the conversation by writing the next line, speaking as "A". Q: Is the tooth fairy real? A: Of course, sweetie. Wrap up your tooth and put it under your pillow tonight. There might be something waiting for you in the morning. Q: Will Santa bring me presents on Christmas? | D41: ➤ | E41: =claudeMessages(C41, 'Tutorial How-To'!$E$37,"temperature",0) -> A: Yes, my dear, as long as you've been good this year, Santa will be sure to bring you presents on Christmas! Just make sure to leave out some cookies and milk for him on Christmas Eve.
C44: User: In the bustling town of Emerald Hills, a diverse group of individuals made their mark. Sarah Martinez, a dedicated nurse, was known for her compassionate care at the local hospital. David Thompson, an innovative software engineer, worked tirelessly on groundbreaking projects that would revolutionize the tech industry. Meanwhile, Emily Nakamura, a talented artist and muralist, painted vibrant and thought-provoking pieces that adorned the walls of buildings and galleries alike. Lastly, Michael O'Connell, an ambitious entrepreneur, opened a unique, eco-friendly cafe that quickly became the town's favorite meeting spot. Each of these individuals contributed to the rich tapestry of the Emerald Hills community. <individuals> 1. Sarah Martinez [NURSE] 2. David Thompson [SOFTWARE ENGINEER] 3. Emily Nakamura [ARTIST] 4. Michael O'Connell [ENTREPRENEUR] </individuals> At the heart of the town, Chef Oliver Hamilton has transformed the culinary scene with his farm-to-table restaurant, Green Plate. Oliver's dedication to sourcing local, organic ingredients has earned the establishment rave reviews from food critics and locals alike. Just down the street, you'll find the Riverside Grove Library, where head librarian Elizabeth Chen has worked diligently to create a welcoming and inclusive space for all. Her efforts to expand the library's offerings and establish reading programs for children have had a significant impact on the town's literacy rates. As you stroll through the charming town square, you'll be captivated by the beautiful murals adorning the walls. These masterpieces are the work of renowned artist, Isabella Torres, whose talent for capturing the essence of Riverside Grove has brought the town to life. Riverside Grove's athletic achievements are also worth noting, thanks to former Olympic swimmer-turned-coach, Marcus Jenkins. Marcus has used his experience and passion to train the town's youth, leading the Riverside Grove Swim Team to several regional championships. <individuals> 1. Oliver Hamilton [CHEF] 2. Elizabeth Chen [LIBRARIAN] 3. Isabella Torres [ARTIST] 4. Marcus Jenkins [COACH] </individuals> Oak Valley, a charming small town, is home to a remarkable trio of individuals whose skills and dedication have left a lasting impact on the community. At the town's bustling farmer's market, you'll find Laura Simmons, a passionate organic farmer known for her delicious and sustainably grown produce. Her dedication to promoting healthy eating has inspired the town to embrace a more eco-conscious lifestyle. In Oak Valley's community center, Kevin Alvarez, a skilled dance instructor, has brought the joy of movement to people of all ages. His inclusive dance classes have fostered a sense of unity and self-expression among residents, enriching the local arts scene. Lastly, Rachel O'Connor, a tireless volunteer, dedicates her time to various charitable initiatives. Her commitment to improving the lives of others has been instrumental in creating a strong sense of community within Oak Valley. Through their unique talents and unwavering dedication, Laura, Kevin, and Rachel have woven themselves into the fabric of Oak Valley, helping to create a vibrant and thriving small town. Assistant: <individuals> | D44: ➤ | E44: =claudeMessages(C44, 'Tutorial How-To'!$E$37,"temperature",0) -> 1. Laura Simmons [ORGANIC FARMER] 2. Kevin Alvarez [DANCE INSTRUCTOR] 3. Rachel O'Connor [VOLUNTEER] </individuals>
B50: ← Chapter 6 Exercises: Precognition (Thinking Step by Step) | E50: Chapter 7 Exercises: Using Examples →
B52: Back to top ↑
B53: Table of Contents

Sheet 7 - Exercises Using Examples (F
B1: Chapter 7: Using Examples (Few-Shot Prompting) - Exercises
B3: Page Contents
C4: Exercise 7.1 - Email Formatting via Examples
B6: Exercise 7.1 - Email Formatting via Examples | I6: Back to top ↑
B7: We're going to redo Exercise 2 in Chapter 6, but this time, we're going to edit the yellow-highlighted Prompt Template box to use "few-shot" examples of emails + proper classification (and formatting) to get Claude to output the correct answer. We want the last letter of Claude's output to be the letter of the category. Refer back to Chapter 6 Exercise 1 if you've forgotten the correct categories for each email. Claude's response will turn GREEN if your prompt yields the correct answer.
B9: Remember that these are the categories for the emails:
C10: (A) Pre-sale question (B) Broken or defective item (C) Billing question (D) Other (please explain)
E12: Input {{EMAIL}} | G12: Prompt After Substitution | I12: Claude's Response | K12: Last Letter
C13: User: You are an email classification assistant. Classify the email into ONE of the following categories. Do NOT include explanations. Output ONLY the category letter. <categories> (A) Pre-sale question (B) Broken or defective item (C) Billing question (D) Other </categories> Here are examples of correct formatting: <examples> Email: How much does the Mixmaster4000 cost? Answer: A Email: My Mixmaster won’t turn on. Answer: B Email: Please remove me from your mailing list. Answer: D </examples> Now classify the following email: Email: {{EMAIL}} Answer: | D13: ﹢ | E13: Hi -- My Mixmaster4000 is producing a strange noise when I operate it. It also smells a bit smoky and plasticky, like burning electronics. I need a replacement. | F13: ＝ | G13: =substitute($C$13,"{{EMAIL}}",E13) -> User: You are an email classification assistant. Classify the email into ONE of the following categories. Do NOT include explanations. Output ONLY the category letter. <categories> (A) Pre-sale question (B) Broken or defective item (C) Billing question (D) Other </categories> Here are examples of correct formatting: <examples> Email: How much does the Mixmaster4000 cost? Answer: A Email: My Mixmaster won’t turn on. Answer: B Email: Please remove me from your mailing list. Answer: D </examples> Now classify the following email: Email: Hi -- My Mixmaster4000 is producing a strange noise when I operate it. It also smells a bit smoky and plasticky, like burning electronics. I need a replacement. Answer: | H13: ➤ | I13: =claudeMessages(G13,'Tutorial How-To'!$E$37,"temperature",0) -> B | K13: =RIGHT(I13, 1) -> B
D16: ﹢ | E16: Can I use my Mixmaster 4000 to mix paint, or is it only meant for mixing food? | F16: ＝ | G16: =substitute($C$13,"{{EMAIL}}",E16) -> User: You are an email classification assistant. Classify the email into ONE of the following categories. Do NOT include explanations. Output ONLY the category letter. <categories> (A) Pre-sale question (B) Broken or defective item (C) Billing question (D) Other </categories> Here are examples of correct formatting: <examples> Email: How much does the Mixmaster4000 cost? Answer: A Email: My Mixmaster won’t turn on. Answer: B Email: Please remove me from your mailing list. Answer: D </examples> Now classify the following email: Email: Can I use my Mixmaster 4000 to mix paint, or is it only meant for mixing food? Answer: | H16: ➤ | I16: =claudeMessages(G16,'Tutorial How-To'!$E$37,"temperature",0) -> A | K16: =RIGHT(I16, 1) -> A
D19: ﹢ | E19: I HAVE BEEN WAITING 4 MONTHS FOR MY MONTHLY CHARGES TO END AFTER CANCELLING!! WTF IS GOING ON??? | F19: ＝ | G19: =substitute($C$13,"{{EMAIL}}",E19) -> User: You are an email classification assistant. Classify the email into ONE of the following categories. Do NOT include explanations. Output ONLY the category letter. <categories> (A) Pre-sale question (B) Broken or defective item (C) Billing question (D) Other </categories> Here are examples of correct formatting: <examples> Email: How much does the Mixmaster4000 cost? Answer: A Email: My Mixmaster won’t turn on. Answer: B Email: Please remove me from your mailing list. Answer: D </examples> Now classify the following email: Email: I HAVE BEEN WAITING 4 MONTHS FOR MY MONTHLY CHARGES TO END AFTER CANCELLING!! WTF IS GOING ON??? Answer: | H19: ➤ | I19: =claudeMessages(G19,'Tutorial How-To'!$E$37,"temperature",0) -> C | K19: =RIGHT(I19, 1) -> C
D22: ﹢ | E22: How did I get here I am not good with computer. Halp. | F22: ＝ | G22: =substitute($C$13,"{{EMAIL}}",E22) -> User: You are an email classification assistant. Classify the email into ONE of the following categories. Do NOT include explanations. Output ONLY the category letter. <categories> (A) Pre-sale question (B) Broken or defective item (C) Billing question (D) Other </categories> Here are examples of correct formatting: <examples> Email: How much does the Mixmaster4000 cost? Answer: A Email: My Mixmaster won’t turn on. Answer: B Email: Please remove me from your mailing list. Answer: D </examples> Now classify the following email: Email: How did I get here I am not good with computer. Halp. Answer: | H22: ➤ | I22: =claudeMessages(G22,'Tutorial How-To'!$E$37,"temperature",0) -> D | K22: =RIGHT(I22, 1) -> D
B25: ❓ | C25: If you need a hint, click on the plus sign (➕) on the far left of this row.
B26: Hint: You're going to have to write some example emails and classify them for Claude (with the exact formatting you want). There are multiple ways to do this. Here are some guidelines below.
B27: 1. | C27: Try to have at least two example emails. Claude doesn't need an example for all categories, and the examples don't have to be long. It's more helpful to have examples for whatever you think the trickier categories are (which you were asked to think about at the bottom of Chapter 6 Exercise 1). XML tags will help you separate out your examples from the rest of your prompt, although it's unnecessary.
B28: 2. | C28: Make sure your example answer formatting is exactly the format you want Claude to use, so Claude can emulate the format as well. This format should make it so that Claude's answer ends in the letter of the category. Wherever you put the {{EMAIL}} placeholder, make sure that it's formatted exactly like your example emails.
B29: 3. | C29: Make sure you still have the categories listed within the prompt itself, otherwise Claude won't know what categories to reference, as well as {{EMAIL}} as a placeholder for substitution.
B30: The conditional formatting of this exercise is looking for a response where the very last character of your response is the correct categorization letter ("B", "C", etc.). The letters in column K should match the letters in the blue cells in the chapter 6.1 exercise.
B32: ⁉️ | C32: Still stuck? Click on the plus sign (➕) on the far left of this row for the answer.
B33: Answer: Below is one way you could go about doing this.
C35: Prompt Template ANSWER | I35: Step in Hint
C36: User: Please classify emails into the following categories, and do not include explanations: <categories> (A) Pre-sale question (B) Broken or defective item (C) Billing question (D) Other (please explain) </categories> Here are a few examples of correct answer formatting: <examples> Q: How much does it cost to buy a Mixmaster4000? A: The correct category is: A Q: My Mixmaster won't turn on. A: The correct category is: B Q: Please remove me from your mailing list. A: The correct category is: D </examples> Here is the email for you to categorize: {{EMAIL}} Assistant: The correct category is: | I36: 1. Have at least two example emails
I37: 2. Have correct answer formatting
I38: 4. Have {{EMAIL}} + categories
B44: ← Chapter 7: Using Examples (Few-Shot Prompting) | I44: Chapter 8: Avoiding Hallucinations →
B46: Back to top ↑
B47: Table of Contents

Sheet 8 - Avoiding Hallucinations
B1: Chapter 8: Avoiding Hallucinations | G1: -
B3: Page Contents
C4: Lesson
C5: Examples
C6: Example Playground
B8: Lesson | E8: Back to top ↑
B9: Some bad news: Claude sometimes "hallucinates" and makes claims that are untrue or unjustified. The good news: there are techniques you can use to minimize hallucinations.
B11: Below, we'll go over a few of these techniques, namely:
B12: - | C12: Giving Claude the option to say it doesn't know the answer to a question
B13: - | C13: Asking Claude to find evidence before answering
B14: However, there are many methods to avoid hallucinations, including many of the techniques you've already learned in this course. If Claude hallucinates, experiment with multiple techniques to get Claude to increase its accuracy.
B16: Examples | E16: Back to top ↑
B17: Here is a question about general factual knowledge in answer to which Claude hallucinates several large hippos because it's trying to be as helpful as possible.
C19: Prompt | E19: Claude's Response
C20: User: Who is the heaviest hippo of all time? | D20: ➤ | E20: =claudeMessages(C20, 'Tutorial How-To'!$E$37,"temperature",0) -> Unfortunately, there doesn't seem to be a definitive record for the heaviest hippo of all time. Hippos are known to be one of the largest land animals, but their exact weights can vary significantly. Some key points about hippo weights: - Hippos are sexually dimorphic, meaning male hippos are typically much larger than females. Adult male hippos can weigh between 3,000-9,000 lbs (1,360-4,080 kg), while females are usually 3,000-5,000 lbs (1,360-2,270 kg). - The largest recorded wild hippo was a male shot in Uganda in 1926, which weighed around 9,920 lbs (4,500 kg). However, this weight is not definitively confirmed. - In captivity, some exceptionally large hippos have been recorded, such as a male named Ubangi at the San Diego Zoo who weighed around 9,920 lbs (4,500 kg) in the 1970s. - Overall, the heaviest hippo on record is difficult to pin down, as comprehensive weight data for wild hippos is limited. The largest confirmed weights are likely in the 9,000-10,000 lb (4,000-4,500 kg) range for exceptionally large adult male hippos. But the true "heaviest hippo of all time" remains uncertain.
B22: A solution we can try here is to "give Claude an out" — tell Claude that it's OK for it to decline to answer, or to only answer if it actually knows the answer with certainty.
C24: Prompt | E24: Claude's Response
C25: User: Who is the heaviest hippo of all time? Only answer if you know the answer with certainty. | D25: ➤ | E25: =claudeMessages(C25, 'Tutorial How-To'!$E$37,"temperature",0) -> I do not have definitive information about the heaviest hippo of all time. Hippo weights can vary significantly, and without access to comprehensive records, I cannot state with certainty who the heaviest hippo was. Hippo weights are not as well-documented as some other animals, so I do not want to provide an unverified claim.
B27: In the prompt below, we give Claude a long document containing some "distractor information" that is almost but not quite relevant to the user's question. Without prompting help, Claude falls for the distractor information and gives an incorrect "hallucinated" answer as to the size of Matterport's subscriber base as of May 31, 2020. Note: As you'll learn later in the next chapter, it's best practice to have the question at the bottom after any text or document, but we put it at the top here to make the prompt easier to read. Feel free to double click on the prompt cell to get the full prompt text (it's very long!).
C29: Prompt | E29: Claude's Response
C30: User: <question>What was Matterport's subscriber base on the precise date of May 31, 2020?</question> Please read the below document. Then write a brief numerical answer inside <answer> tags. <document> Matterport SEC filing 10-K 2023 Item 1. Business Our Company Matterport is leading the digitization and datafication of the built world. We believe the digital transformation of the built world will fundamentally change the way people interact with buildings and the physical spaces around them. Since its founding in 2011, Matterport’s pioneering technology has set the standard for digitizing, accessing and managing buildings, spaces and places online. Our platform’s innovative software, spatial data-driven data science, and 3D capture technology have broken down the barriers that have kept the largest asset class in the world, buildings and physical spaces, offline and underutilized for many years. We believe the digitization and datafication of the built world will continue to unlock significant operational efficiencies and property values, and that Matterport is the platform to lead this enormous global transformation. The world is rapidly moving from offline to online. Digital transformation has made a powerful and lasting impact across every business and industry today. According to International Data Corporation, or IDC, over $6.8 trillion of direct investments will be made on digital transformation from 2020 to 2023, the global digital transformation spending is forecasted to reach $3.4 trillion in 2026 with a five-year compound annual growth rate (“CAGR”) of 16.3%, and digital twin investments are expected to have a five-year CAGR of 35.2%. With this secular shift, there is also growing demand for the built world to transition from physical to digital. Nevertheless, the vast majority of buildings and spaces remain offline and undigitized. The global building stock, estimated by Savills to be $327 trillion in total property value as of 2021, remains largely offline today, and we estimate that less than 0.1% is penetrated by digital transformation. Matterport was among the first to recognize the increasing need for digitization of the built world and the power of spatial data, the unique details underlying buildings and spaces, in facilitating the understanding of buildings and spaces. In the past, technology advanced physical road maps to the data-rich, digital maps and location services we all rely on today. Matterport now digitizes buildings, creating a data-rich environment to vastly increase our understanding and the full potential of each and every space we capture. Just as we can instantly, at the touch of a button, learn the fastest route from one city to another or locate the nearest coffee shops, Matterport’s spatial data for buildings unlocks a rich set of insights and learnings about properties and spaces worldwide. In addition, just as the geo-spatial mapping platforms of today have opened their mapping data to industry to create new business models such as ridesharing, e-commerce, food delivery marketplaces, and even short-term rental and home sharing, open access to Matterport’s structured spatial data is enabling new opportunities and business models for hospitality, facilities management, insurance, construction, real estate and retail, among others. We believe the total addressable market opportunity for digitizing the built world is over $240 billion, and could be as high as $1 trillion as the market matures at scale. This is based on our analysis, modeling and understanding of the global building stock of over 4 billion properties and 20 billion spaces in the world today. With the help of artificial intelligence (“AI”), machine learning (“ML”) and deep learning (“DL”) technologies, we believe that, with the additional monetization opportunities from powerful spatial data-driven property insights and analytics, the total addressable market for the digitization and datafication of the built world will reach more than $1 trillion. Our spatial data platform and capture of digital twins deliver value across a diverse set of industries and use cases. Large retailers can manage thousands of store locations remotely, real estate agencies can provide virtual open houses for hundreds of properties and thousands of visitors at the same time, property developers can monitor the entirety of the construction process with greater detail and speed, and insurance companies can more precisely document and evaluate claims and underwriting assessments with efficiency and precision. Matterport delivers the critical digital experience, tools and information that matter to our subscribers about properties of virtually any size, shape, and location worldwide. For nearly a decade, we have been growing our spatial data platform and expanding our capabilities in order to create the most detailed, accurate, and data-rich digital twins available. Moreover, our 3D reconstruction process is fully automated, allowing our solution to scale with equal precision to millions of buildings and spaces of any type, shape, and size in the world. The universal applicability of our service provides Matterport significant scale and reach across diverse verticals and any geography. As of December 31, 2022, our subscriber base had grown approximately 39% to over 701,000 subscribers from 503,000 subscribers as of December 31, 2021, with our digital twins reaching more than 170 countries. We have digitized more than 28 billion square feet of space across multiple industries, representing significant scale and growth over the rest of the market. As we continue to transform buildings into data worldwide, we are extending our spatial data platform to further transform property planning, development, management and intelligence for our subscribers across industries to become the de facto building and business intelligence engine for the built world. We believe the demand for spatial data and resulting insights for enterprises, businesses and institutions across industries, including real estate, architecture, engineering and construction (“AEC”), retail, insurance and government, will continue to grow rapidly. We believe digitization and datafication represent a tremendous greenfield opportunity for growth across this massive category and asset class. From the early stages of design and development to marketing, operations, insurance and building repair and maintenance, our platform’s software and technology provide subscribers critical tools and insights to drive cost savings, increase revenues and optimally manage their buildings and spaces. We believe that hundreds of billions of dollars in unrealized utilization and operating efficiencies in the built world can be unlocked through the power of our spatial data platform. Our platform and data solutions have universal applicability across industries and building categories, giving Matterport a significant advantage as we can address the entirety of this large market opportunity and increase the value of what we believe to be the largest asset class in the world. With a demonstrated track record of delivering value to our subscribers, our offerings include software subscription, data licensing, services and product hardware. As of December 31, 2022, our subscriber base included over 24% of Fortune 1000 companies, with less than 10% of our total revenue generated from our top 10 subscribers. We expect more than 80% of our revenue to come from our software subscription and data license solutions by 2025. Our innovative 3D capture products, the Pro2 and Pro3 Cameras, have played an integral part in shaping the 3D building and property visualization ecosystem. The Pro2 and Pro3 Cameras have driven adoption of our solutions and have generated the unique high-quality and scaled data set that has enabled Cortex, our proprietary AI software engine, to become the pioneering engine for digital twin creation. With this data advantage initially spurred by the Pro2 Camera, we have developed a capture device agnostic platform that scales and can generate new building and property insights for our subscribers across industries and geographies. We have recently experienced rapid growth. Our subscribers have grown approximately 49-fold from December 31, 2018 to December 31, 2022. Our revenue increased by approximately 22% to $136.1 million for the year ended December 31, 2022, from approximately $111.2 million for the year ended December 31, 2021. Our gross profit decreased by $8.1 million or 14%, to $51.8 million for the year ended December 31, 2022, from $60.0 million for the year ended December 31, 2021, primarily attributable to certain disruptive and incremental costs due to the global supply chain constraints in fiscal year 2022. Our ability to retain and grow the subscription revenue generated by our existing subscribers is an important measure of the health of our business and our future growth prospects. We track our performance in this area by measuring our net dollar expansion rate from the same set of customers across comparable periods. Our net dollar expansion rate of 103% for the three months ended December 31, 2022 demonstrates the stickiness and growth potential of our platform. Our Industry and Market Opportunity Today, the vast majority of buildings and spaces remain undigitized. We estimate our current serviceable addressable market includes approximately 1.3 billion spaces worldwide, primarily from the real estate and travel and hospitality sectors. With approximately 9.2 million spaces under management as of December 31, 2022, we are continuing to penetrate the global building stock and expand our footprint across various end markets, including residential and commercial real estate, facilities management, retail, AEC, insurance and repair, and travel and hospitality. We estimate our total addressable market to be more than 4 billion buildings and 20 billion spaces globally, yielding a more than $240 billion market opportunity. We believe that as Matterport’s unique spatial data library and property data services continue to grow, this opportunity could increase to more than $1 trillion based on the size of the building stock and the untapped value creation available to buildings worldwide. The constraints created by the COVID-19 pandemic have only reinforced and accelerated the importance of our scaled 3D capture solution that we have developed for diverse industries and markets over the past decade. Our Spatial Data Platform Overview Our technology platform uses spatial data collected from a wide variety of digital capture devices to transform physical buildings and spaces into dimensionally accurate, photorealistic digital twins that provide our subscribers access to previously unavailable building information and insights. As a first mover in this massive market for nearly a decade, we have developed and scaled our industry-leading 3D reconstruction technology powered by Cortex, our proprietary AI-driven software engine that uses machine learning to recreate a photorealistic, 3D virtual representation of an entire building structure, including contents, equipment and furnishings. The finished product is a detailed and dynamic replication of the physical space that can be explored, analyzed and customized from a web browser on any device, including smartphones. The power to manage even large-scale commercial buildings is in the palm of each subscriber’s hands, made possible by our advanced technology and breakthrough innovations across our entire spatial data technology stack. Key elements of our spatial data platform include: •Bringing offline buildings online. Traditionally, our customers needed to conduct in-person site visits to understand and assess their buildings and spaces. While photographs and floor plans can be helpful, these forms of two-dimensional (“2D”) representation have limited information and tend to be static and rigid, and thus lack the interactive element critical to a holistic understanding of each building and space. With the AI-powered capabilities of Cortex, our proprietary AI software, representation of physical objects is no longer confined to static 2D images and physical visits can be eliminated. Cortex helps to move the buildings and spaces from offline to online and makes them accessible to our customers in real-time and on demand from anywhere. After subscribers scan their buildings, our visualization algorithms accurately infer spatial positions and depths from flat, 2D imagery captured through the scans and transform them into high- fidelity and precise digital twin models. This creates a fully automated image processing pipeline to ensure that each digital twin is of professional grade image quality. •Driven by spatial data. We are a data-driven company. Each incremental capture of a space grows the richness and depth of our spatial data library. Spatial data represents the unique and idiosyncratic details that underlie and compose the buildings and spaces in the human- made environment. Cortex uses the breadth of the billions of data points we have accumulated over the years to improve the 3D accuracy of our digital twins. We help our subscribers pinpoint the height, location and other characteristics of objects in their digital twin. Our sophisticated algorithms also deliver significant commercial value to our subscribers by generating data-based insights that allow them to confidently make assessments and decisions about their properties. For instance, property developers can assess the amount of natural heat and daylight coming from specific windows, retailers can ensure each store layout is up to the same level of code and brand requirements, and factories can insure machinery layouts meet specifications and location guidelines. With approximately 9.2 million spaces under management as of December 31, 2022, our spatial data library is the clearinghouse for information about the built world. •Powered by AI and ML. Artificial intelligence and machine learning technologies effectively utilize spatial data to create a robust virtual experience that is dynamic, realistic, interactive, informative and permits multiple viewing angles. AI and ML also make costly cameras unnecessary for everyday scans—subscribers can now scan their spaces by simply tapping a button on their smartphones. As a result, Matterport is a device agnostic platform, helping us more rapidly scale and drive towards our mission of digitizing and indexing the built world. Our value proposition to subscribers is designed to serve the entirety of the digital building lifecycle, from design and build to maintenance and operations, promotion, sale, lease, insure, repair, restore, secure and finance. As a result, we believe we are uniquely positioned to grow our revenue with our subscribers as we help them to discover opportunities to drive short- and long-term return on investment by taking their buildings and spaces from offline to online across their portfolios of properties. Ubiquitous Capture Matterport has become the standard for 3D space capture. Our technology platform empowers subscribers worldwide to quickly, easily and accurately digitize, customize and manage interactive and dimensionally accurate digital twins of their buildings and spaces. The Matterport platform is designed to work with a wide range of LiDAR, spherical, 3D and 360 cameras, as well as smartphones, to suit the capture needs of all of our subscribers. This provides the flexibility to capture a space of any size, scale, and complexity, at anytime and anywhere. •Matterport Pro3 is our newest 3D camera that scans properties faster than earlier versions to help accelerate project completion. Pro3 provides the highest accuracy scans of both indoor and outdoor spaces and is designed for speed, fidelity, versatility and accuracy. Capturing 3D data up to 100 meters away at less than 20 seconds per sweep, Pro3’s ultra-fast, high-precision LiDAR sensor can run for hours and takes millions of measurements in any conditions. •Matterport Pro2 is our proprietary 3D camera that has been used to capture millions of spaces around the world with a high degree of fidelity, precision, speed and simplicity. Capable of capturing buildings more than 500,000 square feet in size, it has become the camera of choice for many residential, commercial, industrial and large-scale properties. •360 Cameras. Matterport supports a selection of 360 cameras available in the market. These affordable, pocket sized devices deliver precision captures with high fidelity and are appropriate for capturing smaller homes, condos, short-term rentals, apartments, and more. The spherical lens image capture technology of these devices gives Cortex robust, detailed image data to transform panoramas into our industry-leading digital twins. •LEICA BLK360. Through our partnership with Leica, our 3D reconstruction technology and our AI powered software engine, Cortex, transform this powerful LiDAR camera into an ultra-precise capture device for creating Matterport digital twins. It is the solution of choice for AEC professionals when exacting precision is required. •Smartphone Capture. Our capture apps are commercially available for both iOS and Android. Matterport’s smartphone capture solution has democratized 3D capture, making it easy and accessible for anyone to digitize buildings and spaces with a recent iPhone device since the initial introduction of Matterport for iPhone in May 2020. In April 2021, we announced the official release of the Android Capture app, giving Android users the ability to quickly and easily capture buildings and spaces in immersive 3D. In February 2022, we launched Matterport Axis, a motorized mount that holds a smartphone and can be used with the Matterport Capture app to capture 3D digital twins of any physical space with increased speed, precision, and consistency. Cortex and 3D Reconstruction (the Matterport Digital Twin) With a spatial data library, as of December 31, 2022, of approximately 9.2 million spaces under management, representing approximately 28 billion captured square feet of space, we use our advanced ML and DL technologies to algorithmically transform the spatial data we capture into an accurate 3D digital reproduction of any physical space. This intelligent, automated 3D reconstruction is made possible by Cortex, our AI-powered software engine that includes a deep learning neural network that uses our spatial data library to understand how a building or space is divided into floors and rooms, where the doorways and openings are located, and what types of rooms are present, such that those forms are compiled and aligned with dimensional accuracy into a dynamic, photorealistic digital twin. Other components of Cortex include AI-powered computer vision technologies to identify and classify the contents inside a building or space, and object recognition technologies to identify and segment everything from furnishings and equipment to doors, windows, light fixtures, fire suppression sprinklers and fire escapes. Our highly scalable artificial intelligence platform enables our subscribers to tap into powerful, enhanced building data and insights at the click of a button. The Science Behind the Matterport Digital Twin: Cortex AI Highlights Matterport Runs on Cortex Cortex is our AI-powered software engine that includes a precision deep learning neural network to create digital twins of any building or space. Developed using our proprietary spatial data captured with our Pro2 and Pro3 cameras, Cortex delivers a high degree of precision and accuracy while enabling 3D capture using everyday devices. Generic neural networks struggle with 3D reconstruction of the real world. Matterport-optimized networks deliver more accurate and robust results. More than just raw training data, Matterport’s datasets allow us to develop new neural network architectures and evaluate them against user behavior and real-world data in millions of situations. •Deep learning: Connecting and optimizing the detailed neural network data architecture of each space is key to creating robust, highly accurate 3D digital twins. Cortex evaluates and optimizes each 3D model against Matterport’s rich spatial data aggregated from millions of buildings and spaces and the human annotations of those data provided by tens of thousands of subscribers worldwide. Cortex’s evaluative abilities and its data-driven optimization of 3D reconstruction yield consistent, high-precision results across a wide array of building configurations, spaces and environments. •Dynamic 3D reconstruction: Creating precise 3D spatial data at scale from 2D visuals and static images requires a combination of photorealistic, detailed data from multiple viewpoints and millions of spaces that train and optimize Cortex’s neural network and learning capabilities for improved 3D reconstruction of any space. Cortex’s capabilities combined with real-time spatial alignment algorithms in our 3D capture technology create an intuitive “preview” of any work in progress, allowing subscribers to work with their content interactively and in real-time. •Computer vision: Cortex enables a suite of powerful features to enhance the value of digital twins. These include automatic measurements for rooms or objects in a room, automatic 2D-from-3D high-definition photo gallery creation, auto face blurring for privacy protection, custom videos, walkthroughs, auto room labeling and object recognition. •Advanced image processing: Matterport’s computational photography algorithms create a fully automated image processing pipeline to help ensure that each digital twin is of professional grade image quality. Our patented technology makes 3D capture as simple as pressing a single button. Matterport’s software and technology manage the remaining steps, including white balance and camera-specific color correction, high dynamic range tone mapping, de-noising, haze removal, sharpening, saturation and other adjustments to improve image quality. Spatial Data and AI-Powered Insights Every Matterport digital twin contains extensive information about a building, room or physical space. The data uses our AI-powered Cortex engine. In addition to the Matterport digital twin itself, our spatial data consists of precision building geometry and structural detail, building contents, fixtures and condition, along with high-definition imagery and photorealistic detail from many vantage points in a space. Cortex employs a technique we call deep spatial indexing. Deep spatial indexing uses artificial intelligence, computer vision and deep learning to identify and convey important details about each space, its structure and its contents with precision and fidelity. We have created a robust spatial data standard that enables Matterport subscribers to harness an interoperable digital system of record for any building. In addition to creating a highly interactive digital experience for subscribers through the construction of digital twins, we ask ourselves two questions for every subscriber: (1) what is important about their building or physical space and (2) what learnings and insights can we deliver for this space? Our AI-powered Cortex engine helps us answer these questions using our spatial data library to provide aggregated property trends and operational and valuation insights. Moreover, as the Matterport platform ecosystem continues to expand, our subscribers, partners and other third-party developers can bring their own tools to further the breadth and depth of insights they can harvest from our rich spatial data layer. Extensible Platform Ecosystem Matterport offers the largest and most accurate library of spatial data in the world, with, as of December 31, 2022, approximately 9.2 million spaces under management and approximately 28 billion captured square feet. The versatility of our spatial data platform and extensive enterprise software development kit and application programming interfaces (“APIs”) has allowed us to develop a robust global ecosystem of channels and partners that extend the Matterport value proposition by geography and vertical market. We intend to continue to deploy a broad set of workflow integrations with our partners and their subscribers to promote an integrated Matterport solution across our target markets. We are also developing a third-party software marketplace to extend the power of our spatial data platform with easy-to-deploy and easy-to-access Matterport software add-ons. The marketplace enables developers to build new applications and spatial data mining tools, enhance the Matterport 3D experience, and create new productivity and property management tools that supplement our core offerings. These value-added capabilities created by third-party developers enable a scalable new revenue stream, with Matterport sharing the subscription and services revenue from each add-on that is deployed to subscribers through the online marketplace. The network effects of our platform ecosystem contributes to the growth of our business, and we believe that it will continue to bolster future growth by enhancing subscriber stickiness and user engagement. Examples of Matterport add-ons and extensions include: •Add-ons: Encircle (easy-to-use field documentation tools for faster claims processing); WP Matterport Shortcode (free Wordpress plugin that allows Matterport to be embedded quickly and easily with a Matterport shortcode), WP3D Models (WordPress + Matterport integration plugin); Rela (all-in-one marketing solution for listings); CAPTUR3D (all-in-one Content Management System that extends value to Matterport digital twins); Private Model Emded (feature that allows enterprises to privately share digital twins with a large group of employees on the corporate network without requiring additional user licenses); Views (new workgroup collaboration framework to enable groups and large organizations to create separate, permissions-based workflows to manage different tasks with different teams); and Guided Tours and Tags (tool to elevate the visitor experience by creating directed virtual tours of any commercial or residential space tailored to the interests of their visitors). We unveiled our private beta integration with Amazon Web Services (AWS) IoT TwinMaker to enable enterprise customers to seamlessly connect IoT data into visually immersive and dimensionally accurate Matterport digital twin. •Services: Matterport ADA Compliant Digital Twin (solution to provide American Disability Act compliant digital twins) and Enterprise Cloud Software Platform (reimagined cloud software platform for the enterprise that creates, publishes, and manages digital twins of buildings and spaces of any size of shape, indoors or outdoors). Our Competitive Strengths We believe that we have a number of competitive strengths that will enable our market leadership to grow. Our competitive strengths include: •Breadth and depth of the Matterport platform. Our core strength is our all-in-one spatial data platform with broad reach across diverse verticals and geographies such as capture to processing to industries without customization. With the ability to integrate seamlessly with various enterprise systems, our platform delivers value across the property lifecycle for diverse end markets, including real estate, AEC, travel and hospitality, repair and insurance, and industrial and facilities. As of December 31, 2022, our global reach extended to subscribers in more than 170 countries, including over 24% of Fortune 1000 companies. •Market leadership and first-mover advantage. Matterport defined the category of digitizing and datafying the built world almost a decade ago, and we have become the global leader in the category. As of December 31, 2022, we had over 701,000 subscribers on our platform and approximately 9.2 million spaces under management. Our leadership is primarily driven by the fact that we were the first mover in digital twin creation. As a result of our first mover advantage, we have amassed a deep and rich library of spatial data that continues to compound and enhance our leadership position. •Significant network effect. With each new capture and piece of data added to our platform, the richness of our dataset and the depth of insights from our spaces under management grow. In addition, the combination of our ability to turn data into insights with incremental data from new data captures by our subscribers enables Matterport to develop features for subscribers to our platform. We were a first mover in building a spatial data library for the built world, and our leadership in gathering and deriving insights from data continues to compound and the relevance of those insights attracts more new subscribers. •Massive spatial data library as the raw material for valuable property insights. The scale of our spatial data library is a significant advantage in deriving insights for our subscribers. Our spatial data library serves as vital ground truth for Cortex, enabling Matterport to create powerful 3D digital twins using a wide range of camera technology, including low-cost digital and smartphone cameras. As of December 31, 2022, our data came from approximately 9.2 million spaces under management and approximately 28 billion captured square feet. As a result, we have taken property insights and analytics to new levels, benefiting subscribers across various industries. For example, facilities managers significantly reduce the time needed to create building layouts, leading to a significant decrease in the cost of site surveying and as-built modeling. AEC subscribers use the analytics of each as-built space to streamline documentation and collaborate with ease. •Global reach and scale. We are focused on continuing to expand our AI-powered spatial data platform worldwide. We have a significant presence in North America, Europe and Asia, with leadership teams and a go-to-market infrastructure in each of these regions. We have offices in London, Singapore and several across the United States, and we are accelerating our international expansion. As of December 31, 2022, we had over 701,000 subscribers in more than 170 countries. We believe that the geography-agnostic nature of our spatial data platform is a significant advantage as we continue to grow internationally. •Broad patent portfolio supporting 10 years of R&D and innovation. As of December 31, 2022, we had 54 issued and 37 pending patent applications. Our success is based on almost 10 years of focus on innovation. Innovation has been at the center of Matterport, and we will continue to prioritize our investments in R&D to further our market leading position. •Superior capture technology. Matterport’s capture technology platform is a software framework that enables support for a wide variety of capture devices required to create a Matterport digital twin of a building or space. This includes support for LiDAR cameras, 360 cameras, smartphones, Matterport Axis and the Matterport Pro2 and Pro3 cameras. The Pro2 camera was foundational to our spatial data advantage, and we have expanded that advantage with an array of Matterport-enabled third-party capture devices. In August 2022, we launched and began shipment of our Pro3 Camera along with major updates to our industry-leading digital twin cloud platform. The Matterport Pro3 Camera is an advanced 3D capture device, which includes faster boot time, swappable batteries, and a lighter design. The Pro3 camera can perform both indoors and outdoors and is designed for speed, fidelity, versatility and accuracy. Along with our Pro2 Camera, we expect that future sales of our Pro3 Camera will continue to drive increased adoption of our solutions. Matterport is democratizing the 3D capture experience, making high-fidelity and high-accuracy 3D digital twins readily available for any building type and any subscriber need in the property life cycle. While there are other 3D capture solution providers, very few can produce true, dimensionally accurate 3D results, and fewer still can automatically create a final product in photorealistic 3D, and at global scale. This expansive capture technology offering would not be possible without our rich spatial data library available to train the AI-powered Cortex engine to automatically generate accurate digital twins from photos captured with a smartphone or 360 camera. </document> | D30: ➤ | E30: =claudeMessages(C30, 'Tutorial How-To'!$E$37,"temperature",0) -> <answer>503,000</answer>
B34: How do we fix this? Well, a great way to reduce hallucinations on long documents is to make Claude gather evidence first. In this case, we tell Claude to first extract relevant quotes, then base its answer on those quotes. Telling Claude to do so here makes it correctly notice that the quote does not answer the question.
C36: Prompt | E36: Claude's Response
